[
  {
    "animationUrl": null,
    "authenticated": true,
    "authorId": "clb17jx4r0013mb0jgivpgal4",
    "autographed": false,
    "backImage": "https://arweave.net/0PqAYzVTM7QbT_ILera-DBzSHWjS7wvr0pF_r38d9lg",
    "blockchain": "Solana",
    "burnId": "cm9w4asgm21wkwuhzgo4ig4y0",
    "category": "Pokemon",
    "centering": null,
    "collectorId": null,
    "corners": null,
    "createdAt": "2025-04-30T02:33:28.168Z",
    "edges": null,
    "frontImage": "https://arweave.net/j9Hd_GxXGMIL6HvIsIfoWs_CckTXMmWHTrWz9FgXLCc",
    "grade": "Pristine 10",
    "gradeNum": 10,
    "gradingCompany": "CGC",
    "gradingID": "6022863024",
    "id": "2025043028C16600",
    "insuredValue": "70",
    "itemName": "2021 #2 Blastoise CGC 10 Perfect Pokemon | Celebrations - Classic Coll., Base Set - Holo",
    "location": [
      "PSA Vault",
      "Collector Crypt (102006143)",
      "900 West Basin Rd",
      "New Castle, DE 19720"
    ],
    "nftAddress": "4z3feA2PP4LuE4sK56iqEjEc1XoLcs1VSYxbrCwShrA3",
    "nftCategory": null,
    "nftStatus": "Valid",
    "orientation": "vertical",
    "ownerId": "cm7plxeje0a2d1347u1ctbev0",
    "qualifiers": [],
    "ReasonForRejection": null,
    "serial": "2",
    "status": "Transferred",
    "submissionID": "1",
    "suggestPrice": null,
    "surface": null,
    "type": "Card",
    "updatedAt": "2025-09-06T19:36:03.061Z",
    "vault": "PSA Vault",
    "vaultId": "170747776",
    "year": 2021,
    "set": null,
    "format": null,
    "productCode": null,
    "packCount": null,
    "language": null,
    "platform": null,
    "rating": null,
    "series": null,
    "features": null,
    "publisher": null,
    "nftStandard": null,
    "images": {
      "back": "https://arweave.net/0PqAYzVTM7QbT_ILera-DBzSHWjS7wvr0pF_r38d9lg",
      "backM": "https://d1xpxki1g4htqu.cloudfront.net/waJiA91dzlkEbW2kcxYNAYkauaBe-hHXoACz_uVNNEE",
      "backS": "https://d1xpxki1g4htqu.cloudfront.net/uOuYIy2nhyWryNMxD3ELHa6AlCcwBNzQmQz-VWF0cSY",
      "front": "https://arweave.net/j9Hd_GxXGMIL6HvIsIfoWs_CckTXMmWHTrWz9FgXLCc",
      "frontM": "https://d1xpxki1g4htqu.cloudfront.net/OtI5sSyaQeO6XMT3oU_GIDg8ffYLCMSILRPRTO6ae6g",
      "frontS": "https://d1xpxki1g4htqu.cloudfront.net/1kjqn6QlNoRhenvxC7lTSs_aeARmMbSW8CGzEoS338Y"
    },
    "listing": null,
    "offers": [],
    "owner": {
      "id": "cm7plxeje0a2d1347u1ctbev0",
      "name": null,
      "wallet": ""
    }
  },
  {
    "animationUrl": null,
    "authenticated": true,
    "authorId": "clb17jx4r0013mb0jgivpgal4",
    "autographed": false,
    "backImage": "https://arweave.net/p2LsgRQbB0VcHAaWl0FB2GwaeCjBJW8c8ipeOYdGGe8",
    "blockchain": "Solana",
    "burnId": "cm9w4asgm21wkwuhzgo4ig4y0",
    "category": "Pokemon",
    "centering": null,
    "collectorId": null,
    "corners": null,
    "createdAt": "2025-04-30T02:33:26.913Z",
    "edges": null,
    "frontImage": "https://arweave.net/6qJ0MP7pyov6b9LllS1CEk61Rx7hKAA82-ogLwaZGVM",
    "grade": "9.5-Gem Mint",
    "gradeNum": 9.5,
    "gradingCompany": "Beckett",
    "gradingID": "0017782440",
    "id": "2025043026C16599",
    "insuredValue": "69",
    "itemName": "2024 #205 Vaporeon ex BGS 9.5 Scarlet & Violet | Terastal Festival ex, High Class Expansion JPN SAR",
    "location": [
      "PSA Vault",
      "Collector Crypt (102006143)",
      "900 West Basin Rd",
      "New Castle, DE 19720"
    ],
    "nftAddress": "3ssYk9AGdLXFetUqVDz5Gqub7a6kRYGaw3c2wrTHf5FK",
    "nftCategory": null,
    "nftStatus": "Valid",
    "orientation": "vertical",
    "ownerId": "cm7plxeje0a2d1347u1ctbev0",
    "qualifiers": [],
    "ReasonForRejection": null,
    "serial": "205",
    "status": "Transferred",
    "submissionID": "1",
    "suggestPrice": null,
    "surface": null,
    "type": "Card",
    "updatedAt": "2025-09-06T19:43:36.253Z",
    "vault": "PSA Vault",
    "vaultId": "170747862",
    "year": 2024,
    "set": null,
    "format": null,
    "productCode": null,
    "packCount": null,
    "language": null,
    "platform": null,
    "rating": null,
    "series": null,
    "features": null,
    "publisher": null,
    "nftStandard": null,
    "images": {
      "back": "https://arweave.net/p2LsgRQbB0VcHAaWl0FB2GwaeCjBJW8c8ipeOYdGGe8",
      "backM": "https://d1xpxki1g4htqu.cloudfront.net/NHb_YYxeFFSZmXUXgutQG9op2jgoSGf4pp1Vz0WWTBA",
      "backS": "https://d1xpxki1g4htqu.cloudfront.net/XP9AqgskJnLSfOkl7T3fvRSul6FDqGmZhVLWFmIBEbg",
      "front": "https://arweave.net/6qJ0MP7pyov6b9LllS1CEk61Rx7hKAA82-ogLwaZGVM",
      "frontM": "https://d1xpxki1g4htqu.cloudfront.net/s7YLz6ytKqedsnTXi3P95YVknvX8YUZARqLXZC0zkjA",
      "frontS": "https://d1xpxki1g4htqu.cloudfront.net/2lFyfgg8EM0gFF9ktwMOEATG2N9wfSoTY1Ca1qW7eKA"
    },
    "listing": null,
    "offers": [],
    "owner": {
      "id": "cm7plxeje0a2d1347u1ctbev0",
      "name": null,
      "wallet": ""
    }
  },
  {
    "animationUrl": null,
    "authenticated": true,
    "authorId": "clb17jx4r0013mb0jgivpgal4",
    "autographed": false,
    "backImage": "https://arweave.net/6QOxCkg6Zi3g0VB6HySqujCphdj-v9X1qZS7cLxaTaE",
    "blockchain": "Solana",
    "burnId": "cm9w4asgm21wkwuhzgo4ig4y0",
    "category": "Pokemon",
    "centering": null,
    "collectorId": null,
    "corners": null,
    "createdAt": "2025-04-30T02:33:22.769Z",
    "edges": null,
    "frontImage": "https://arweave.net/5q7gOV4reFurhm_yYAoy02S2AaLNPfyYOGV-LyyAE-8",
    "grade": "Pristine 10",
    "gradeNum": 10,
    "gradingCompany": "CGC",
    "gradingID": "6024532014",
    "id": "2025043022C16596",
    "insuredValue": "44",
    "itemName": "2021 #021 Kyogre CGC 10 Perfect Pokemon | Shining Fates, Amazing Rare - Holo",
    "location": [
      "PSA Vault",
      "Collector Crypt (102006143)",
      "900 West Basin Rd",
      "New Castle, DE 19720"
    ],
    "nftAddress": "2phPdgQkcbgJXkZScMracTsUQX2h6Xzc4HmoSae6R7kz",
    "nftCategory": null,
    "nftStatus": "Valid",
    "orientation": "vertical",
    "ownerId": "cm7plxeje0a2d1347u1ctbev0",
    "qualifiers": [],
    "ReasonForRejection": null,
    "serial": "021",
    "status": "Transferred",
    "submissionID": "1",
    "suggestPrice": null,
    "surface": null,
    "type": "Card",
    "updatedAt": "2025-09-06T19:36:06.754Z",
    "vault": "PSA Vault",
    "vaultId": "170741454",
    "year": 2021,
    "set": null,
    "format": null,
    "productCode": null,
    "packCount": null,
    "language": null,
    "platform": null,
    "rating": null,
    "series": null,
    "features": null,
    "publisher": null,
    "nftStandard": null,
    "images": {
      "back": "https://arweave.net/6QOxCkg6Zi3g0VB6HySqujCphdj-v9X1qZS7cLxaTaE",
      "backM": "https://d1xpxki1g4htqu.cloudfront.net/7zcK5MNZXihx5RAEsLSyjkGymT_SEdb2dutd7yel0kc",
      "backS": "https://d1xpxki1g4htqu.cloudfront.net/LDzHGeBKFW7LWb_kXL0f-EnRyL2zM3Z5m8YoDP-1lkY",
      "front": "https://arweave.net/5q7gOV4reFurhm_yYAoy02S2AaLNPfyYOGV-LyyAE-8",
      "frontM": "https://d1xpxki1g4htqu.cloudfront.net/N8HihAp0OcECsmmsYD7f3bLCP9KGReOyKwoMyP62YXM",
      "frontS": "https://d1xpxki1g4htqu.cloudfront.net/WxbGPbg16XL7IAnVVbGedtxvSiq-GrgHwKgnCmj-iqE"
    },
    "listing": null,
    "offers": [],
    "owner": {
      "id": "cm7plxeje0a2d1347u1ctbev0",
      "name": null,
      "wallet": ""
    }
  },
  {
    "animationUrl": null,
    "authenticated": true,
    "authorId": "clb17jx4r0013mb0jgivpgal4",
    "autographed": false,
    "backImage": "https://arweave.net/J7iZrWHHAAx6TsLfiMXfuwbIwA5Tssf6NfIQV8PJle0",
    "blockchain": "Solana",
    "burnId": "cm9w4asgm21wkwuhzgo4ig4y0",
    "category": "Pokemon",
    "centering": null,
    "collectorId": null,
    "corners": null,
    "createdAt": "2025-04-30T02:33:21.533Z",
    "edges": null,
    "frontImage": "https://arweave.net/kK94J6c978IKdgvMrKHyXBEr2aGoFqtN-M9jVFri95A",
    "grade": "Gem Mint 10",
    "gradeNum": 10,
    "gradingCompany": "CGC",
    "gradingID": "6022973083",
    "id": "2025043021C16595",
    "insuredValue": "44",
    "itemName": "2019 #095 Slowpoke & Psyduck GX CGC 10 Gem Mint Pokemon Japanese | Miracle Twin, Super Rare - Holo",
    "location": [
      "PSA Vault",
      "Collector Crypt (102006143)",
      "900 West Basin Rd",
      "New Castle, DE 19720"
    ],
    "nftAddress": "8cHTUEfJ2WX1LicHtcVRkZ7B2SFhcJnnXBKVGAQDLVqy",
    "nftCategory": null,
    "nftStatus": "Valid",
    "orientation": "vertical",
    "ownerId": "cm7plxeje0a2d1347u1ctbev0",
    "qualifiers": [],
    "ReasonForRejection": null,
    "serial": "095",
    "status": "Transferred",
    "submissionID": "1",
    "suggestPrice": null,
    "surface": null,
    "type": "Card",
    "updatedAt": "2025-09-06T19:37:24.826Z",
    "vault": "PSA Vault",
    "vaultId": "170744403",
    "year": 2019,
    "set": null,
    "format": null,
    "productCode": null,
    "packCount": null,
    "language": null,
    "platform": null,
    "rating": null,
    "series": null,
    "features": null,
    "publisher": null,
    "nftStandard": null,
    "images": {
      "back": "https://arweave.net/J7iZrWHHAAx6TsLfiMXfuwbIwA5Tssf6NfIQV8PJle0",
      "backM": "https://d1xpxki1g4htqu.cloudfront.net/DaHxI7lBS2KpzJYgp46d7V_teHWsUDe3ZTD1tOytdSQ",
      "backS": "https://d1xpxki1g4htqu.cloudfront.net/0ZRD_ygfHf-9wgdkOS5AWnThM0Tzb3dDkMkcE0lE9AY",
      "front": "https://arweave.net/kK94J6c978IKdgvMrKHyXBEr2aGoFqtN-M9jVFri95A",
      "frontM": "https://d1xpxki1g4htqu.cloudfront.net/axhLuxt6NCN4-l4OXbgv0uoFEmPBU_EuPUIzQT3Z3OU",
      "frontS": "https://d1xpxki1g4htqu.cloudfront.net/ymPUpIdbrEs_IUbJjwpdSK8CbDJgLlVlzJ-BEpMsDC8"
    },
    "listing": null,
    "offers": [],
    "owner": {
      "id": "cm7plxeje0a2d1347u1ctbev0",
      "name": null,
      "wallet": ""
    }
  },
  {
    "animationUrl": null,
    "authenticated": true,
    "authorId": "clb17jx4r0013mb0jgivpgal4",
    "autographed": false,
    "backImage": "https://arweave.net/2zp-fvis3a-hKj4_RKVM04h2IF8ihfHlHFsCIvImQBE",
    "blockchain": "Solana",
    "burnId": "cm861yrof1pazuhxbzyeioeu7",
    "category": "Pokemon",
    "centering": null,
    "collectorId": null,
    "corners": null,
    "createdAt": "2025-04-30T02:33:20.254Z",
    "edges": null,
    "frontImage": "https://arweave.net/oM7NK8F_oY54wf5DUKbUEmj-4zWy13iDoNDHSIw_xfk",
    "grade": "Gem Mint 9.5",
    "gradeNum": 9.5,
    "gradingCompany": "CGC",
    "gradingID": "4221808004",
    "id": "2025043020C16594",
    "insuredValue": "513",
    "itemName": "1999 #4 Dragonite CGC 9.5 Fossil | Unlimited - Additional Ink",
    "location": [
      "PSA Vault",
      "Collector Crypt (102006143)",
      "900 West Basin Rd",
      "New Castle, DE 19720"
    ],
    "nftAddress": "DT85Yv1ERTd4jXaCujwU1iABNpzkwUyZNvrsyRvKt3cn",
    "nftCategory": null,
    "nftStatus": "Valid",
    "orientation": "vertical",
    "ownerId": "cm7plxeje0a2d1347u1ctbev0",
    "qualifiers": [],
    "ReasonForRejection": null,
    "serial": "4",
    "status": "Transferred",
    "submissionID": "1",
    "suggestPrice": null,
    "surface": null,
    "type": "Card",
    "updatedAt": "2025-09-06T19:56:48.594Z",
    "vault": "PSA Vault",
    "vaultId": "170690446",
    "year": 1999,
    "set": null,
    "format": null,
    "productCode": null,
    "packCount": null,
    "language": null,
    "platform": null,
    "rating": null,
    "series": null,
    "features": null,
    "publisher": null,
    "nftStandard": null,
    "images": {
      "back": "https://arweave.net/2zp-fvis3a-hKj4_RKVM04h2IF8ihfHlHFsCIvImQBE",
      "backM": "https://d1xpxki1g4htqu.cloudfront.net/huQx4bsGau-EHh1d5c57pw4JR9hgn6CixG93MQqIKrA",
      "backS": "https://d1xpxki1g4htqu.cloudfront.net/7-td-ElXYFaom1vK4yAGIv0TqMjuYPIJHZ5dobbxjso",
      "front": "https://arweave.net/oM7NK8F_oY54wf5DUKbUEmj-4zWy13iDoNDHSIw_xfk",
      "frontM": "https://d1xpxki1g4htqu.cloudfront.net/fB8hKM8vOUEigczRQoUL5NSi9Mq-UEEZDvSVTjAsZwc",
      "frontS": "https://d1xpxki1g4htqu.cloudfront.net/h6g-ShUlBrvJxx2p3kkhpOf6WGiMQC3uM8V4HWDTFzI"
    },
    "listing": null,
    "offers": [],
    "owner": {
      "id": "cm7plxeje0a2d1347u1ctbev0",
      "name": null,
      "wallet": ""
    }
  },
  {
    "animationUrl": null,
    "authenticated": true,
    "authorId": "clb17jx4r0013mb0jgivpgal4",
    "autographed": false,
    "backImage": "https://arweave.net/NrRJ1rHb7OKPM625w8crxoaH1QDiowkDnKC6szX1KTk",
    "blockchain": "Solana",
    "burnId": "cm7l4ui1s09yr66u9jqmitc3v",
    "category": "Pokemon",
    "centering": null,
    "collectorId": null,
    "corners": null,
    "createdAt": "2025-04-30T02:33:18.006Z",
    "edges": null,
    "frontImage": "https://arweave.net/0R7RhSNzQikUJuX0HG8h-WNuWDh4GZdsIOVqH48j2OY",
    "grade": "GEM-MT 10",
    "gradeNum": 10,
    "gradingCompany": "PSA",
    "gradingID": "110076366",
    "id": "2025043017C16592",
    "insuredValue": "370",
    "itemName": "2025 #087 CYNTHIA'S GARCHOMP EX PSA 10 POKEMON JAPANESE SV9a-HEAT WAVE ARENA | SPECIAL ART RARE",
    "location": [
      "PSA Vault",
      "Collector Crypt (102006143)",
      "900 West Basin Rd",
      "New Castle, DE 19720"
    ],
    "nftAddress": "6ouBRrho4vBQe6Gq3oevwbLtJFN8uBzkaJZFALYpShLo",
    "nftCategory": null,
    "nftStatus": "Valid",
    "orientation": "vertical",
    "ownerId": "cm7plxeje0a2d1347u1ctbev0",
    "qualifiers": [],
    "ReasonForRejection": null,
    "serial": "087",
    "status": "Transferred",
    "submissionID": "1",
    "suggestPrice": null,
    "surface": null,
    "type": "Card",
    "updatedAt": "2025-09-06T19:37:10.857Z",
    "vault": "PSA Vault",
    "vaultId": "170690441",
    "year": 2025,
    "set": null,
    "format": null,
    "productCode": null,
    "packCount": null,
    "language": null,
    "platform": null,
    "rating": null,
    "series": null,
    "features": null,
    "publisher": null,
    "nftStandard": null,
    "images": {
      "back": "https://arweave.net/NrRJ1rHb7OKPM625w8crxoaH1QDiowkDnKC6szX1KTk",
      "backM": "https://d1xpxki1g4htqu.cloudfront.net/aGw_siA750JT-r9jw3cbCwEp2oHmnC4py5BZ2v8yMzk",
      "backS": "https://d1xpxki1g4htqu.cloudfront.net/vKsvrFmwxwDmbV8fkhMUj_lrrnuNYiJNvYDijWk2M9s",
      "front": "https://arweave.net/0R7RhSNzQikUJuX0HG8h-WNuWDh4GZdsIOVqH48j2OY",
      "frontM": "https://d1xpxki1g4htqu.cloudfront.net/c7DiVav6DqA161-QOXpXuKc5YLgOctMI0jKIVB7nNJg",
      "frontS": "https://d1xpxki1g4htqu.cloudfront.net/D8W4nC-ffeczGEzLjY5nSGtfaWSNrilcy3mN8s0oatA"
    },
    "listing": null,
    "offers": [],
    "owner": {
      "id": "cm7plxeje0a2d1347u1ctbev0",
      "name": null,
      "wallet": ""
    }
  },
  {
    "animationUrl": null,
    "authenticated": true,
    "authorId": "clb17jx4r0013mb0jgivpgal4",
    "autographed": false,
    "backImage": "https://arweave.net/mZCAu9yeRPIH6Zb-2_J5WaylfDT9HaPaPLlVJXlzwok",
    "blockchain": "Solana",
    "burnId": "cm0mqphab0047o8014nsi3hlp",
    "category": "Pokemon",
    "centering": null,
    "collectorId": null,
    "corners": null,
    "createdAt": "2025-04-30T02:33:16.843Z",
    "edges": null,
    "frontImage": "https://arweave.net/WvpjY8V7wtGk7pKYcJ3lLcZ6N6cm039SrJ7T2hHfD9E",
    "grade": "GEM-MT 10",
    "gradeNum": 10,
    "gradingCompany": "PSA",
    "gradingID": "52175780",
    "id": "2025043016C16591",
    "insuredValue": "16094",
    "itemName": "2006 #052 CHARIZARD-HOLO PSA 10 POKEMON JAPANESE DRAGON FRONTIERS | GOLD STAR",
    "location": [
      "PSA Vault",
      "Collector Crypt (102006143)",
      "900 West Basin Rd",
      "New Castle, DE 19720"
    ],
    "nftAddress": "CKqH2kMJRiL8TijS19QfASbownmSzP7s7yMdMhG89tF",
    "nftCategory": null,
    "nftStatus": "Valid",
    "orientation": "vertical",
    "ownerId": "cm0mqphaa0046o80125sly1q1",
    "qualifiers": [],
    "ReasonForRejection": null,
    "serial": "052",
    "status": "Transferred",
    "submissionID": "1",
    "suggestPrice": null,
    "surface": null,
    "type": "Card",
    "updatedAt": "2025-09-06T19:52:39.614Z",
    "vault": "PSA Vault",
    "vaultId": "170641745",
    "year": 2006,
    "set": null,
    "format": null,
    "productCode": null,
    "packCount": null,
    "language": null,
    "platform": null,
    "rating": null,
    "series": null,
    "features": null,
    "publisher": null,
    "nftStandard": null,
    "images": {
      "back": "https://arweave.net/mZCAu9yeRPIH6Zb-2_J5WaylfDT9HaPaPLlVJXlzwok",
      "backM": "https://d1xpxki1g4htqu.cloudfront.net/-fGyREMyhHFoiqt784qLDxB7Lp81rLrpR_Z3RzE2JIA",
      "backS": "https://d1xpxki1g4htqu.cloudfront.net/HbOaW0LTU4503TS-yzv92YZEws-AeFv_iTEQnsc8gho",
      "front": "https://arweave.net/WvpjY8V7wtGk7pKYcJ3lLcZ6N6cm039SrJ7T2hHfD9E",
      "frontM": "https://d1xpxki1g4htqu.cloudfront.net/Ma3kw40XSjyp5PI6bNyaZ-FDT2eBBjVQikFu1pVbEzw",
      "frontS": "https://d1xpxki1g4htqu.cloudfront.net/QF_yAucFD1UY4Q7j-M7fS6bp08RciOujJ4f-Y2D7UDk"
    },
    "listing": null,
    "offers": [],
    "owner": {
      "id": "cm0mqphaa0046o80125sly1q1",
      "name": "moonfrog",
      "wallet": "7RHyrnqNqTBx8hco3SBtuu3LjFZ59cWgUV5wwDSiFpiA"
    }
  },
  {
    "animationUrl": null,
    "authenticated": true,
    "authorId": "clb17jx4r0013mb0jgivpgal4",
    "autographed": false,
    "backImage": "https://arweave.net/LduK5f9pugT2mRWbvJyCNdSejOWC2ngfTnT5McIKW1k",
    "blockchain": "Solana",
    "burnId": "cm9jdnrhl1k39145giiej97jq",
    "category": "Pokemon",
    "centering": null,
    "collectorId": null,
    "corners": null,
    "createdAt": "2025-04-30T02:33:15.997Z",
    "edges": null,
    "frontImage": "https://arweave.net/q9jdzXcD6VVbufUXGlqZ_dM0TUSt1k2A12R_ZEEv2ic",
    "grade": "GEM-MT 10",
    "gradeNum": 10,
    "gradingCompany": "PSA",
    "gradingID": "105080938",
    "id": "2025043015C16590",
    "insuredValue": "764",
    "itemName": "2023 #199 CHARIZARD EX PSA 10 POKEMON MEW EN-151 | SPECIAL ILLUSTRATION RARE",
    "location": [
      "PSA Vault",
      "Collector Crypt (102006143)",
      "900 West Basin Rd",
      "New Castle, DE 19720"
    ],
    "nftAddress": "GhyyfgCFCcj1PSXfAGCHtWG8sqsQ8JCmdKESmQ4zhpKi",
    "nftCategory": null,
    "nftStatus": "Valid",
    "orientation": "vertical",
    "ownerId": "cm7plxeje0a2d1347u1ctbev0",
    "qualifiers": [],
    "ReasonForRejection": null,
    "serial": "199",
    "status": "Transferred",
    "submissionID": "1",
    "suggestPrice": null,
    "surface": null,
    "type": "Card",
    "updatedAt": "2025-09-06T19:37:21.089Z",
    "vault": "PSA Vault",
    "vaultId": "170641741",
    "year": 2023,
    "set": null,
    "format": null,
    "productCode": null,
    "packCount": null,
    "language": null,
    "platform": null,
    "rating": null,
    "series": null,
    "features": null,
    "publisher": null,
    "nftStandard": null,
    "images": {
      "back": "https://arweave.net/LduK5f9pugT2mRWbvJyCNdSejOWC2ngfTnT5McIKW1k",
      "backM": "https://d1xpxki1g4htqu.cloudfront.net/8b9NIVoBnj4diNWWOBxb9JnmHd4FqaBxCrf_Yor-I1c",
      "backS": "https://d1xpxki1g4htqu.cloudfront.net/T0zLIueuu7Kn8np1FT7YFm9zL_0ffsUDCZf2mcmucHI",
      "front": "https://arweave.net/q9jdzXcD6VVbufUXGlqZ_dM0TUSt1k2A12R_ZEEv2ic",
      "frontM": "https://d1xpxki1g4htqu.cloudfront.net/4n0o8BLP-us2TXHrh4EgGmcD6lIdV_QuHU4P1hlGuok",
      "frontS": "https://d1xpxki1g4htqu.cloudfront.net/kjWKyZocSguOjefSDCJl_RaG0uZ3FWCjXywPU9GyKPM"
    },
    "listing": null,
    "offers": [],
    "owner": {
      "id": "cm7plxeje0a2d1347u1ctbev0",
      "name": null,
      "wallet": ""
    }
  },
  {
    "animationUrl": null,
    "authenticated": true,
    "authorId": "clb17jx4r0013mb0jgivpgal4",
    "autographed": false,
    "backImage": "https://arweave.net/0vekbSblFg4uGhCCm0Dq12CjX9gdAYFgP5nTNhmAKc4",
    "blockchain": "Solana",
    "burnId": "cm0mqphab0047o8014nsi3hlp",
    "category": "Pokemon",
    "centering": null,
    "collectorId": null,
    "corners": null,
    "createdAt": "2025-04-30T02:33:13.070Z",
    "edges": null,
    "frontImage": "https://arweave.net/-BRApOAvmct1zkWJhsVzYvyR4PNcTfaJjObOk0r8w94",
    "grade": "MINT 9",
    "gradeNum": 9,
    "gradingCompany": "PSA",
    "gradingID": "71125373",
    "id": "2025043013C16587",
    "insuredValue": "265",
    "itemName": "2015 #159 FULL ART/M MEWTWO EX PSA 9 POKEMON XY BREAKTHROUGH",
    "location": [
      "PSA Vault",
      "Collector Crypt (102006143)",
      "900 West Basin Rd",
      "New Castle, DE 19720"
    ],
    "nftAddress": "yyGqvtuvs4Gdi66op2TZpHKXEkLEM5e1imDPwzFsHgK",
    "nftCategory": null,
    "nftStatus": "Valid",
    "orientation": "vertical",
    "ownerId": "cm7plxeje0a2d1347u1ctbev0",
    "qualifiers": [],
    "ReasonForRejection": null,
    "serial": "159",
    "status": "Transferred",
    "submissionID": "1",
    "suggestPrice": null,
    "surface": null,
    "type": "Card",
    "updatedAt": "2025-09-06T19:21:00.640Z",
    "vault": "PSA Vault",
    "vaultId": "170641744",
    "year": 2015,
    "set": null,
    "format": null,
    "productCode": null,
    "packCount": null,
    "language": null,
    "platform": null,
    "rating": null,
    "series": null,
    "features": null,
    "publisher": null,
    "nftStandard": null,
    "images": {
      "back": "https://arweave.net/0vekbSblFg4uGhCCm0Dq12CjX9gdAYFgP5nTNhmAKc4",
      "backM": "https://d1xpxki1g4htqu.cloudfront.net/_bZqvF-QzqL7vdTDFGrwMxaQnGu0Z7E5-AGw9h2wVhc",
      "backS": "https://d1xpxki1g4htqu.cloudfront.net/u-L-0rUQ7nUbQpWLh0BkZG-wez88a53dXhyy8ERx3eI",
      "front": "https://arweave.net/-BRApOAvmct1zkWJhsVzYvyR4PNcTfaJjObOk0r8w94",
      "frontM": "https://d1xpxki1g4htqu.cloudfront.net/7c3RjlzQN9ptutUtyxXh-NUt4jU-7XguN1RJpch-vzU",
      "frontS": "https://d1xpxki1g4htqu.cloudfront.net/YHoYj1CoBGRojDODBTEe0pJa3TG8pkF23xU8HfVqW4Q"
    },
    "listing": null,
    "offers": [],
    "owner": {
      "id": "cm7plxeje0a2d1347u1ctbev0",
      "name": null,
      "wallet": ""
    }
  },
  {
    "animationUrl": null,
    "authenticated": true,
    "authorId": "clb17jx4r0013mb0jgivpgal4",
    "autographed": false,
    "backImage": "https://arweave.net/M5j3ImnhPyk_7Oar16FlXWlX5Yx8K3fSxxanh_j1ZSQ",
    "blockchain": "Solana",
    "burnId": "cm0cwqq530ukipb018hdn02q2",
    "category": "Pokemon",
    "centering": null,
    "collectorId": null,
    "corners": null,
    "createdAt": "2025-04-30T02:33:06.183Z",
    "edges": null,
    "frontImage": "https://arweave.net/xCaxHeXYWLG43IrO77lFutt0A8b7mNDppntf88P3G6I",
    "grade": "GEM-MT 10",
    "gradeNum": 10,
    "gradingCompany": "PSA",
    "gradingID": "103592610",
    "id": "202504306C16581",
    "insuredValue": "359",
    "itemName": "2023 #GG69 FULL ART/GIRATINA VSTAR PSA 10 POKEMON SWORD AND SHIELD CROWN ZENITH | SECRET",
    "location": [
      "PSA Vault",
      "Collector Crypt (102006143)",
      "900 West Basin Rd",
      "New Castle, DE 19720"
    ],
    "nftAddress": "3fWQe9K3594Q887sLoHuibtaWgyBXk54y85EekeDE3Ep",
    "nftCategory": null,
    "nftStatus": "Valid",
    "orientation": "vertical",
    "ownerId": "cm0cwqq520ukhpb01us1nmmhz",
    "qualifiers": [],
    "ReasonForRejection": null,
    "serial": "GG69",
    "status": "Transferred",
    "submissionID": "1",
    "suggestPrice": null,
    "surface": null,
    "type": "Card",
    "updatedAt": "2025-09-06T19:37:19.480Z",
    "vault": "PSA Vault",
    "vaultId": "170622952",
    "year": 2023,
    "set": null,
    "format": null,
    "productCode": null,
    "packCount": null,
    "language": null,
    "platform": null,
    "rating": null,
    "series": null,
    "features": null,
    "publisher": null,
    "nftStandard": null,
    "images": {
      "back": "https://arweave.net/M5j3ImnhPyk_7Oar16FlXWlX5Yx8K3fSxxanh_j1ZSQ",
      "backM": "https://d1xpxki1g4htqu.cloudfront.net/u5a62fWfDE70mR6flnl77DudOnsh-nzPQV9vb_fqZWE",
      "backS": "https://d1xpxki1g4htqu.cloudfront.net/H7laFaNjo3WqIKeyLy2zUf5qIfCMOOQvJOur0TIfBzY",
      "front": "https://arweave.net/xCaxHeXYWLG43IrO77lFutt0A8b7mNDppntf88P3G6I",
      "frontM": "https://d1xpxki1g4htqu.cloudfront.net/cXODEI-uB1fBCOdrz_uEG5fOz9qypWYcW4by68KbPC4",
      "frontS": "https://d1xpxki1g4htqu.cloudfront.net/NxHSxbtLmDCJ3VteTKuNqNFCJYY-C4-3Wkqi5Pn4e80"
    },
    "listing": null,
    "offers": [],
    "owner": {
      "id": "cm0cwqq520ukhpb01us1nmmhz",
      "name": "",
      "wallet": "CMhUqwibkmdkZ3UpNDAffLY1p5CngZHDwtMvNGCMhkhc"
    }
  },
  {
    "animationUrl": null,
    "authenticated": true,
    "authorId": "clb17jx4r0013mb0jgivpgal4",
    "autographed": false,
    "backImage": "https://arweave.net/Tt2NBl7AC4KzB3ZORqhoNE02tMTFlpYnZ5cBhtIbggQ",
    "blockchain": "Solana",
    "burnId": "cm9jdnrhl1k39145giiej97jq",
    "category": "Pokemon",
    "centering": null,
    "collectorId": null,
    "corners": null,
    "createdAt": "2025-04-30T02:33:05.221Z",
    "edges": null,
    "frontImage": "https://arweave.net/mDL8_D65LEM3zkmjZSWTBP7VLEY9AY-nCjGMBluBuTA",
    "grade": "GEM-MT 10",
    "gradeNum": 10,
    "gradingCompany": "PSA",
    "gradingID": "96249732",
    "id": "202504305C16580",
    "insuredValue": "350",
    "itemName": "2023 #222 TYRANITAR PSA 10 POKEMON PAL EN-PALDEA EVOLVED | ILLUSTRATION RARE",
    "location": [
      "PSA Vault",
      "Collector Crypt (102006143)",
      "900 West Basin Rd",
      "New Castle, DE 19720"
    ],
    "nftAddress": "HVCVLse681zMaCiw1EaWbA2twwWvGgDKUj4GHafrWart",
    "nftCategory": null,
    "nftStatus": "Valid",
    "orientation": "vertical",
    "ownerId": "cm9jdnrhl1k38145g4p3g5ucs",
    "qualifiers": [],
    "ReasonForRejection": null,
    "serial": "222",
    "status": "Transferred",
    "submissionID": "1",
    "suggestPrice": null,
    "surface": null,
    "type": "Card",
    "updatedAt": "2025-09-06T19:36:26.533Z",
    "vault": "PSA Vault",
    "vaultId": "170622960",
    "year": 2023,
    "set": null,
    "format": null,
    "productCode": null,
    "packCount": null,
    "language": null,
    "platform": null,
    "rating": null,
    "series": null,
    "features": null,
    "publisher": null,
    "nftStandard": null,
    "images": {
      "back": "https://arweave.net/Tt2NBl7AC4KzB3ZORqhoNE02tMTFlpYnZ5cBhtIbggQ",
      "backM": "https://d1xpxki1g4htqu.cloudfront.net/R9oAdg8TlYyZUdHsThxUiysVRbv-P8GWrTx4yN3mYWY",
      "backS": "https://d1xpxki1g4htqu.cloudfront.net/PCleXDYfwHxLwsQEi3kGbnLclLPQIoMygmHOPiGqXcc",
      "front": "https://arweave.net/mDL8_D65LEM3zkmjZSWTBP7VLEY9AY-nCjGMBluBuTA",
      "frontM": "https://d1xpxki1g4htqu.cloudfront.net/aC3USL3LTmUUz3cpVZytyrWVFY7jr7E26HaKcNwnLvk",
      "frontS": "https://d1xpxki1g4htqu.cloudfront.net/kS2RGfCtfD5RO3DtilE05Yfo8CmsZu3b1z_BnHvB5tE"
    },
    "listing": null,
    "offers": [],
    "owner": {
      "id": "cm9jdnrhl1k38145g4p3g5ucs",
      "name": "",
      "wallet": "5SNFpNqL1Sw8k6As5v16wAMk1sjnVua6ULFDHqXDdFUH"
    }
  },
  {
    "animationUrl": null,
    "authenticated": true,
    "authorId": "clb17jx4r0013mb0jgivpgal4",
    "autographed": false,
    "backImage": "https://arweave.net/wrNT9AHIvH-h4wG5cNmzoIKfhbIfl4KDb0r89tfEYFY",
    "blockchain": "Solana",
    "burnId": "cm8nneicz21io142ff3upqtnd",
    "category": "Pokemon",
    "centering": null,
    "collectorId": null,
    "corners": null,
    "createdAt": "2025-04-30T02:33:04.128Z",
    "edges": null,
    "frontImage": "https://arweave.net/vSIBx96nDHpCT9ak-zqT_D2sGog3wfLJkFALzQgiZrw",
    "grade": "MINT 9",
    "gradeNum": 9,
    "gradingCompany": "PSA",
    "gradingID": "105449276",
    "id": "202504304C16579",
    "insuredValue": "340",
    "itemName": "2000 #18 TYPHLOSION-HOLO PSA 9 POKEMON NEO GENESIS 1ST EDITION",
    "location": [
      "PSA Vault",
      "Collector Crypt (102006143)",
      "900 West Basin Rd",
      "New Castle, DE 19720"
    ],
    "nftAddress": "3zsjdUu4CLB6awsR3bzJr5j4ZF6ggQarFhpDUNEoj8CY",
    "nftCategory": null,
    "nftStatus": "Valid",
    "orientation": "vertical",
    "ownerId": "cm8nneicz21in142fap1r3q9q",
    "qualifiers": [],
    "ReasonForRejection": null,
    "serial": "18",
    "status": "Transferred",
    "submissionID": "1",
    "suggestPrice": null,
    "surface": null,
    "type": "Card",
    "updatedAt": "2025-09-06T19:36:26.700Z",
    "vault": "PSA Vault",
    "vaultId": "170622961",
    "year": 2000,
    "set": null,
    "format": null,
    "productCode": null,
    "packCount": null,
    "language": null,
    "platform": null,
    "rating": null,
    "series": null,
    "features": null,
    "publisher": null,
    "nftStandard": null,
    "images": {
      "back": "https://arweave.net/wrNT9AHIvH-h4wG5cNmzoIKfhbIfl4KDb0r89tfEYFY",
      "backM": "https://d1xpxki1g4htqu.cloudfront.net/81Nc21QgxUWmBYGvNiSe9ILQc_pGrU2zUunFX-82uiI",
      "backS": "https://d1xpxki1g4htqu.cloudfront.net/Kb1YmNuSfgw7h4QohSR2cShCFTfGyJsSkienBDwmwSw",
      "front": "https://arweave.net/vSIBx96nDHpCT9ak-zqT_D2sGog3wfLJkFALzQgiZrw",
      "frontM": "https://d1xpxki1g4htqu.cloudfront.net/yAH4VEMB5JJP3oddn20WXmoyblKX8rUlK6yWh99pEws",
      "frontS": "https://d1xpxki1g4htqu.cloudfront.net/-SHZJpTEKwKWNn7GXfGKB_i2IMppVOHHNMHOcrhP-Zw"
    },
    "listing": null,
    "offers": [],
    "owner": {
      "id": "cm8nneicz21in142fap1r3q9q",
      "name": "katp123333",
      "wallet": "DQ5SR2PZoAkrrv2KLFUvAV8NiXqttt4HJtPxrLWTcEGn"
    }
  },
  {
    "animationUrl": null,
    "authenticated": true,
    "authorId": "clb17jx4r0013mb0jgivpgal4",
    "autographed": false,
    "backImage": "https://arweave.net/GZqIIY8a2Rod9i70KJdTEzsKGlbN9J5DO10n2ExjfRU",
    "blockchain": "Solana",
    "burnId": "cmac4lg8l2qfi8ppftblux0wl",
    "category": "Pokemon",
    "centering": null,
    "collectorId": null,
    "corners": null,
    "createdAt": "2025-04-28T22:43:17.776Z",
    "edges": null,
    "frontImage": "https://arweave.net/M_tjffHzBM29A3H5VmQ27hb__MwhK-tEpD221gNT7ZY",
    "grade": "Gem Mint 10",
    "gradeNum": 10,
    "gradingCompany": "CGC",
    "gradingID": "6033181014",
    "id": "2025042817C16571",
    "insuredValue": "3500",
    "itemName": "2016 #231/XY-P Rayquaza Poncho-Wearing Pikachu CGC 10 Pokemon Japanese XY & BREAK Promo",
    "location": [
      "PWCC",
      "PWCC Vault: Collector Crypt #732795",
      "7560 SW Durham Rd",
      "Tigard, OR 97224"
    ],
    "nftAddress": "xiREW1kuhZCFZc4EhzdGN86Ua1E9D8gxbZbspFBrrzV",
    "nftCategory": null,
    "nftStatus": "Valid",
    "orientation": "vertical",
    "ownerId": "cmac4lg8l2qfh8ppfhcw8d8sk",
    "qualifiers": null,
    "ReasonForRejection": null,
    "serial": "231/XY-P",
    "status": "Transferred",
    "submissionID": "1",
    "suggestPrice": null,
    "surface": null,
    "type": "Card",
    "updatedAt": "2025-09-06T19:19:02.447Z",
    "vault": "PWCC",
    "vaultId": "18911542",
    "year": 2016,
    "set": null,
    "format": null,
    "productCode": null,
    "packCount": null,
    "language": null,
    "platform": null,
    "rating": null,
    "series": null,
    "features": null,
    "publisher": null,
    "nftStandard": null,
    "images": {
      "back": "https://arweave.net/GZqIIY8a2Rod9i70KJdTEzsKGlbN9J5DO10n2ExjfRU",
      "backM": "https://d1xpxki1g4htqu.cloudfront.net/yTGhnQ6nnyHAOoQM4c12wdpHLrKTn2ZKEJxSog68pAE",
      "backS": "https://d1xpxki1g4htqu.cloudfront.net/Vu5kR4WwDlUEp7zsbSj5rZOVbkWUT4YSYe5x5B3lBLA",
      "front": "https://arweave.net/M_tjffHzBM29A3H5VmQ27hb__MwhK-tEpD221gNT7ZY",
      "frontM": "https://d1xpxki1g4htqu.cloudfront.net/bx43SD4K0a6It2OFunnv-MH4p-AFazmKuWmTR68_tX0",
      "frontS": "https://d1xpxki1g4htqu.cloudfront.net/4kpzKNY0AwKqCbO-3cEGTCKWzET9BFnzQ6zBAxD44-E"
    },
    "listing": null,
    "offers": [
      {
        "id": "7db38a91-2384-494c-a456-64ca972d1258"
      }
    ],
    "owner": {
      "id": "cmac4lg8l2qfh8ppfhcw8d8sk",
      "name": "jessejpegs",
      "wallet": "4rovijokHGTztMWyNhFzE138eL8x1vb5mnWs7FM8z2pP"
    }
  },
  {
    "animationUrl": null,
    "authenticated": true,
    "authorId": "clb17jx4r0013mb0jgivpgal4",
    "autographed": false,
    "backImage": "https://arweave.net/PcVig4teXbfvj_lc8YyCanlwaxglo7npfX_auclz3qc",
    "blockchain": "Solana",
    "burnId": "cmaezstfd119r6hoas5a5yeb6",
    "category": "Pokemon",
    "centering": null,
    "collectorId": null,
    "corners": null,
    "createdAt": "2025-04-28T22:27:47.909Z",
    "edges": null,
    "frontImage": "https://arweave.net/E6MX7BmaZnZnJkQlo_zEcgksj0QELCGoMa7W0BcqpRg",
    "grade": "MINT 9",
    "gradeNum": 9,
    "gradingCompany": "PSA",
    "gradingID": "89414966",
    "id": "2025042847C16568",
    "insuredValue": "278",
    "itemName": "2022 #186 FULL ART/LUGIA V PSA 9 POKEMON SWORD & SHIELD SILVER TEMPEST",
    "location": [
      "PSA Vault",
      "Collector Crypt (102006143)",
      "900 West Basin Rd",
      "New Castle, DE 19720"
    ],
    "nftAddress": "38R9XyRfg4hokWsAjuzAA9vB6UMYNcfuNwrXyHNS5DQn",
    "nftCategory": null,
    "nftStatus": "Valid",
    "orientation": "vertical",
    "ownerId": "cmaezstfd119q6hoar9s0ymtp",
    "qualifiers": [],
    "ReasonForRejection": null,
    "serial": "186",
    "status": "Transferred",
    "submissionID": "1",
    "suggestPrice": null,
    "surface": null,
    "type": "Card",
    "updatedAt": "2025-09-06T19:39:15.008Z",
    "vault": "PSA Vault",
    "vaultId": "101835401",
    "year": 2022,
    "set": null,
    "format": null,
    "productCode": null,
    "packCount": null,
    "language": null,
    "platform": null,
    "rating": null,
    "series": null,
    "features": null,
    "publisher": null,
    "nftStandard": null,
    "images": {
      "back": "https://arweave.net/PcVig4teXbfvj_lc8YyCanlwaxglo7npfX_auclz3qc",
      "backM": "https://d1xpxki1g4htqu.cloudfront.net/EF4NUtNLfV0E-G7QhS1N0xXDkzUij5BVDqkKWO_Ubvs",
      "backS": "https://d1xpxki1g4htqu.cloudfront.net/lzG2-NS3YE048A_G_g-0dLGfjMREpodFl4L5_H8dFu0",
      "front": "https://arweave.net/E6MX7BmaZnZnJkQlo_zEcgksj0QELCGoMa7W0BcqpRg",
      "frontM": "https://d1xpxki1g4htqu.cloudfront.net/cgO7eSoxlu980cZMKu5oYZO7SOip20lSVPYVmUnxe4E",
      "frontS": "https://d1xpxki1g4htqu.cloudfront.net/v2NJvgRWhVMaqQ5ZYPIE5cDTrLUZOEWQFMaejgk3cIA"
    },
    "listing": null,
    "offers": [],
    "owner": {
      "id": "cmaezstfd119q6hoar9s0ymtp",
      "name": "edo",
      "wallet": "H3RXjGyyZBYEgrLghyU4ERDkUDndni2oaa6B5Vcy2fBV"
    }
  },
  {
    "animationUrl": null,
    "authenticated": true,
    "authorId": "clb17jx4r0013mb0jgivpgal4",
    "autographed": false,
    "backImage": "https://arweave.net/2B2KKKjVXF2QwPq06jazEOYaJ2hoIVyOcn_edlDv9Jg",
    "blockchain": "Solana",
    "burnId": "cm8za0zse5hh4142fjfh6uvep",
    "category": "Pokemon",
    "centering": null,
    "collectorId": null,
    "corners": null,
    "createdAt": "2025-04-28T22:27:43.428Z",
    "edges": null,
    "frontImage": "https://arweave.net/JzwQepcx365p3rDl27gddeLO8Xeg2A2XpR14JCpxWWE",
    "grade": "GEM-MT 10",
    "gradeNum": 10,
    "gradingCompany": "PSA",
    "gradingID": "78667004",
    "id": "2025042843C16562",
    "insuredValue": "117",
    "itemName": "2021 #175 FULL ART/CELEBI V PSA 10 POKEMON JAPANESE S PROMO | JET-BLACK SPIRIT BOOSTER BOX",
    "location": [
      "PSA Vault",
      "Collector Crypt (102006143)",
      "900 West Basin Rd",
      "New Castle, DE 19720"
    ],
    "nftAddress": "9EpT8yJ3tUyNpnpcxwE9vZof7YmffZ9EDPThgwkmZrim",
    "nftCategory": null,
    "nftStatus": "Valid",
    "orientation": "vertical",
    "ownerId": "cm7plxeje0a2d1347u1ctbev0",
    "qualifiers": [],
    "ReasonForRejection": null,
    "serial": "175",
    "status": "Transferred",
    "submissionID": "1",
    "suggestPrice": null,
    "surface": null,
    "type": "Card",
    "updatedAt": "2025-09-06T19:21:16.323Z",
    "vault": "PSA Vault",
    "vaultId": "101835401",
    "year": 2021,
    "set": null,
    "format": null,
    "productCode": null,
    "packCount": null,
    "language": null,
    "platform": null,
    "rating": null,
    "series": null,
    "features": null,
    "publisher": null,
    "nftStandard": null,
    "images": {
      "back": "https://arweave.net/2B2KKKjVXF2QwPq06jazEOYaJ2hoIVyOcn_edlDv9Jg",
      "backM": "https://d1xpxki1g4htqu.cloudfront.net/DWLPuIlqYKhu5oi_cwgEUBECbHT2wLBzum0T_Txdjd0",
      "backS": "https://d1xpxki1g4htqu.cloudfront.net/EApjHS3yIwecNY0gl-glFKtSVcw4OZgvkFkdqosjOIo",
      "front": "https://arweave.net/JzwQepcx365p3rDl27gddeLO8Xeg2A2XpR14JCpxWWE",
      "frontM": "https://d1xpxki1g4htqu.cloudfront.net/eYaAYa2mTkK97P03c9jRRPX_WNpb97ZJ6HlVN5P3UMc",
      "frontS": "https://d1xpxki1g4htqu.cloudfront.net/up7b_vQr1zF4QAobxnSKAILC9aq5y7-XAgBlRMkFzBw"
    },
    "listing": null,
    "offers": [],
    "owner": {
      "id": "cm7plxeje0a2d1347u1ctbev0",
      "name": null,
      "wallet": ""
    }
  },
  {
    "animationUrl": null,
    "authenticated": true,
    "authorId": "clb17jx4r0013mb0jgivpgal4",
    "autographed": false,
    "backImage": "https://arweave.net/apGzMstorbAuVE-wWqKvZMjkGYHUaBHdq9SRjLeg0-0",
    "blockchain": "Solana",
    "burnId": "cm8za0zse5hh4142fjfh6uvep",
    "category": "Pokemon",
    "centering": null,
    "collectorId": null,
    "corners": null,
    "createdAt": "2025-04-28T22:27:41.591Z",
    "edges": null,
    "frontImage": "https://arweave.net/RbZIa0pweAftiHoUIzt-yKa9Pwx0P-CAHn1Q8jIFk-o",
    "grade": "GEM-MT 10",
    "gradeNum": 10,
    "gradingCompany": "PSA",
    "gradingID": "98650365",
    "id": "2025042841C16560",
    "insuredValue": "113",
    "itemName": "2024 #187 CHANSEY PSA 10 POKEMON TWM EN-TWILIGHT MASQUERADE | ILLUSTRATION RARE",
    "location": [
      "PSA Vault",
      "Collector Crypt (102006143)",
      "900 West Basin Rd",
      "New Castle, DE 19720"
    ],
    "nftAddress": "KYXdtCfzgikYZDoVThHmjEMATeZESDedAWonFapNUaD",
    "nftCategory": null,
    "nftStatus": "Valid",
    "orientation": "vertical",
    "ownerId": "cm7plxeje0a2d1347u1ctbev0",
    "qualifiers": [],
    "ReasonForRejection": null,
    "serial": "187",
    "status": "Transferred",
    "submissionID": "1",
    "suggestPrice": null,
    "surface": null,
    "type": "Card",
    "updatedAt": "2025-09-06T19:15:26.428Z",
    "vault": "PSA Vault",
    "vaultId": "101835401",
    "year": 2024,
    "set": null,
    "format": null,
    "productCode": null,
    "packCount": null,
    "language": null,
    "platform": null,
    "rating": null,
    "series": null,
    "features": null,
    "publisher": null,
    "nftStandard": null,
    "images": {
      "back": "https://arweave.net/apGzMstorbAuVE-wWqKvZMjkGYHUaBHdq9SRjLeg0-0",
      "backM": "https://d1xpxki1g4htqu.cloudfront.net/esWCsY1uJtmDMqFzi2g7NhPC4eXVOGcAVPry6a3h9lM",
      "backS": "https://d1xpxki1g4htqu.cloudfront.net/yfkw5JYCQtnGbqU0eHCC_hX7-bBZ-N9hu9dQDAreYE8",
      "front": "https://arweave.net/RbZIa0pweAftiHoUIzt-yKa9Pwx0P-CAHn1Q8jIFk-o",
      "frontM": "https://d1xpxki1g4htqu.cloudfront.net/XdAnXhRAT-L9rDR5OdzOQBNGwMtWD5KQvVk8Ort_MN4",
      "frontS": "https://d1xpxki1g4htqu.cloudfront.net/eBQD9s9UHAJrmY7yjBkbQCsFGVrGUUb2uaHIafuW9z8"
    },
    "listing": null,
    "offers": [],
    "owner": {
      "id": "cm7plxeje0a2d1347u1ctbev0",
      "name": null,
      "wallet": ""
    }
  },
  {
    "animationUrl": null,
    "authenticated": true,
    "authorId": "clb17jx4r0013mb0jgivpgal4",
    "autographed": false,
    "backImage": "https://arweave.net/QWpuwYKdrrJ0PMNvSBwicJNsqtd8AUrdV2hu6VCnFkQ",
    "blockchain": "Solana",
    "burnId": "cmaezstfd119r6hoas5a5yeb6",
    "category": "Pokemon",
    "centering": null,
    "collectorId": null,
    "corners": null,
    "createdAt": "2025-04-28T22:27:40.774Z",
    "edges": null,
    "frontImage": "https://arweave.net/BNAQXvRf3kIQFzZ5yuV1FCxRUPOVnGeu2F8_jeqYJZU",
    "grade": "GEM-MT 10",
    "gradeNum": 10,
    "gradingCompany": "PSA",
    "gradingID": "102200909",
    "id": "2025042840C16559",
    "insuredValue": "99",
    "itemName": "2024 #205 VAPOREON EX PSA 10 POKEMON JAPANESE SV8a-TERASTAL FEST ex | SPECIAL ART RARE",
    "location": [
      "PSA Vault",
      "Collector Crypt (102006143)",
      "900 West Basin Rd",
      "New Castle, DE 19720"
    ],
    "nftAddress": "9XF4FT5Ny7fogC9z66z5J2An5jDCn5F97UfkrvrvjL7",
    "nftCategory": null,
    "nftStatus": "Valid",
    "orientation": "vertical",
    "ownerId": "cm7plxeje0a2d1347u1ctbev0",
    "qualifiers": [],
    "ReasonForRejection": null,
    "serial": "205",
    "status": "Transferred",
    "submissionID": "1",
    "suggestPrice": null,
    "surface": null,
    "type": "Card",
    "updatedAt": "2025-09-06T19:40:54.437Z",
    "vault": "PSA Vault",
    "vaultId": "101835401",
    "year": 2024,
    "set": null,
    "format": null,
    "productCode": null,
    "packCount": null,
    "language": null,
    "platform": null,
    "rating": null,
    "series": null,
    "features": null,
    "publisher": null,
    "nftStandard": null,
    "images": {
      "back": "https://arweave.net/QWpuwYKdrrJ0PMNvSBwicJNsqtd8AUrdV2hu6VCnFkQ",
      "backM": "https://d1xpxki1g4htqu.cloudfront.net/ke-CZT6NB9YzIExFPw3ZBnKyJBacLX2V10tq67PPuRA",
      "backS": "https://d1xpxki1g4htqu.cloudfront.net/BAosPrNdF74_FXBRcdJQMMRucyCXdC775QyZ-q-28jU",
      "front": "https://arweave.net/BNAQXvRf3kIQFzZ5yuV1FCxRUPOVnGeu2F8_jeqYJZU",
      "frontM": "https://d1xpxki1g4htqu.cloudfront.net/WHlTW26nC1uwZjuW5APMSPa8HdS6iAI8gf2Fx_LREos",
      "frontS": "https://d1xpxki1g4htqu.cloudfront.net/gvQh3eBWrqqJAw2SVZzLKsIrArPHCcejIhLmkEPS9dE"
    },
    "listing": null,
    "offers": [],
    "owner": {
      "id": "cm7plxeje0a2d1347u1ctbev0",
      "name": null,
      "wallet": ""
    }
  },
  {
    "animationUrl": null,
    "authenticated": true,
    "authorId": "clb17jx4r0013mb0jgivpgal4",
    "autographed": false,
    "backImage": "https://arweave.net/ckoJjTuyAleQWRV6xQu88FpYuJhAiejfaNeab2FNyhg",
    "blockchain": "Solana",
    "burnId": "cm8za0zse5hh4142fjfh6uvep",
    "category": "Pokemon",
    "centering": null,
    "collectorId": null,
    "corners": null,
    "createdAt": "2025-04-28T22:27:39.849Z",
    "edges": null,
    "frontImage": "https://arweave.net/J1jbMYahA8fga9-P2YvbzJhb5jMuXrzmPRZfZKATOM4",
    "grade": "MINT 9",
    "gradeNum": 9,
    "gradingCompany": "PSA",
    "gradingID": "80549392",
    "id": "2025042839C16558",
    "insuredValue": "93",
    "itemName": "2005 #009 RAYQUAZA-HOLO PSA 9 POKEMON JAPANESE POKEPARK BLUE",
    "location": [
      "PSA Vault",
      "Collector Crypt (102006143)",
      "900 West Basin Rd",
      "New Castle, DE 19720"
    ],
    "nftAddress": "9ZDYp6BSs5ZqSf5WFLnHuVF7eHy2aeBLj85pKfFVnGv9",
    "nftCategory": null,
    "nftStatus": "Valid",
    "orientation": "vertical",
    "ownerId": "cm7plxeje0a2d1347u1ctbev0",
    "qualifiers": [],
    "ReasonForRejection": null,
    "serial": "009",
    "status": "Transferred",
    "submissionID": "1",
    "suggestPrice": null,
    "surface": null,
    "type": "Card",
    "updatedAt": "2025-09-06T19:40:06.460Z",
    "vault": "PSA Vault",
    "vaultId": "101835401",
    "year": 2005,
    "set": null,
    "format": null,
    "productCode": null,
    "packCount": null,
    "language": null,
    "platform": null,
    "rating": null,
    "series": null,
    "features": null,
    "publisher": null,
    "nftStandard": null,
    "images": {
      "back": "https://arweave.net/ckoJjTuyAleQWRV6xQu88FpYuJhAiejfaNeab2FNyhg",
      "backM": "https://d1xpxki1g4htqu.cloudfront.net/92RdIqOOGz3Y-Jp3gHwXN8Al7L0y3JV6O0iIlWiiFlg",
      "backS": "https://d1xpxki1g4htqu.cloudfront.net/Ku5IC4yHSw1ulFHz_YbFVlTvvE7pLFjgWxk9PjwpcWE",
      "front": "https://arweave.net/J1jbMYahA8fga9-P2YvbzJhb5jMuXrzmPRZfZKATOM4",
      "frontM": "https://d1xpxki1g4htqu.cloudfront.net/7LjagO02es73ScwsZQNbqm3G7KVk-RZDRdjkYgvay2U",
      "frontS": "https://d1xpxki1g4htqu.cloudfront.net/Duwgy2I6cXcbcXBlv6JeGguDULRL0LCaWIE0NNdreHE"
    },
    "listing": null,
    "offers": [],
    "owner": {
      "id": "cm7plxeje0a2d1347u1ctbev0",
      "name": null,
      "wallet": ""
    }
  },
  {
    "animationUrl": null,
    "authenticated": true,
    "authorId": "clb17jx4r0013mb0jgivpgal4",
    "autographed": false,
    "backImage": "https://arweave.net/wEsUa1pxLMpO-j_StAg8f0_ZfRTcVeav_hmR7Uf2OvQ",
    "blockchain": "Solana",
    "burnId": "cm8za0zse5hh4142fjfh6uvep",
    "category": "Pokemon",
    "centering": null,
    "collectorId": null,
    "corners": null,
    "createdAt": "2025-04-28T22:27:39.159Z",
    "edges": null,
    "frontImage": "https://arweave.net/RSWx02edFHC0LzdGYCLZsgILxhaJD-dNovFNEAa12aY",
    "grade": "GEM-MT 10",
    "gradeNum": 10,
    "gradingCompany": "PSA",
    "gradingID": "102530641",
    "id": "2025042839C16557",
    "insuredValue": "90",
    "itemName": "2021 #082 FULL ART/KLARA PSA 10 POKEMON JAPANESE SWORD & SHIELD PEERLESS FIGHTERS",
    "location": [
      "PSA Vault",
      "Collector Crypt (102006143)",
      "900 West Basin Rd",
      "New Castle, DE 19720"
    ],
    "nftAddress": "AbJVprgbM2wMEs7eDKjUaLBmuqqtRTpB4h3Mo6AJ8GAp",
    "nftCategory": null,
    "nftStatus": "Valid",
    "orientation": "vertical",
    "ownerId": "cm7plxeje0a2d1347u1ctbev0",
    "qualifiers": [],
    "ReasonForRejection": null,
    "serial": "082",
    "status": "Transferred",
    "submissionID": "1",
    "suggestPrice": null,
    "surface": null,
    "type": "Card",
    "updatedAt": "2025-09-06T19:40:50.664Z",
    "vault": "PSA Vault",
    "vaultId": "101835401",
    "year": 2021,
    "set": null,
    "format": null,
    "productCode": null,
    "packCount": null,
    "language": null,
    "platform": null,
    "rating": null,
    "series": null,
    "features": null,
    "publisher": null,
    "nftStandard": null,
    "images": {
      "back": "https://arweave.net/wEsUa1pxLMpO-j_StAg8f0_ZfRTcVeav_hmR7Uf2OvQ",
      "backM": "https://d1xpxki1g4htqu.cloudfront.net/V5ilTQ_i4WHewLN4Sz-vJz_H8Vuoln9CoD3LTuvnwQM",
      "backS": "https://d1xpxki1g4htqu.cloudfront.net/UFHO_vgqMDtsRrZlysJTbU9S9SsPVhGwmMTmbVLpXmk",
      "front": "https://arweave.net/RSWx02edFHC0LzdGYCLZsgILxhaJD-dNovFNEAa12aY",
      "frontM": "https://d1xpxki1g4htqu.cloudfront.net/WA4hRq5eTkglVq_u6i-KDbXvLT9P863otOD8NhAsL8Y",
      "frontS": "https://d1xpxki1g4htqu.cloudfront.net/uLi4JKCYTqOBEF0QI9UYWP9AVFNpp_sA0Hv-nLhpaSA"
    },
    "listing": null,
    "offers": [],
    "owner": {
      "id": "cm7plxeje0a2d1347u1ctbev0",
      "name": null,
      "wallet": ""
    }
  },
  {
    "animationUrl": null,
    "authenticated": true,
    "authorId": "clb17jx4r0013mb0jgivpgal4",
    "autographed": false,
    "backImage": "https://arweave.net/SLH2WYSOQclzWM4Pn97ZeHOMDLJ9gJDBc-i7nTc93tY",
    "blockchain": "Solana",
    "burnId": "cm8za0zse5hh4142fjfh6uvep",
    "category": "Pokemon",
    "centering": null,
    "collectorId": null,
    "corners": null,
    "createdAt": "2025-04-28T22:27:37.208Z",
    "edges": null,
    "frontImage": "https://arweave.net/gskpS4cmkm9OsrNAKA0DkqzCHoz1fKqMWpGV3q2Elhc",
    "grade": "GEM-MT 10",
    "gradeNum": 10,
    "gradingCompany": "PSA",
    "gradingID": "106686033",
    "id": "2025042837C16555",
    "insuredValue": "85",
    "itemName": "2025 #173 EEVEE PSA 10 POKEMON SVP EN-SV BLACK STAR PROMO | PRISMATIC EVOLUTIONS ELITE TRAINER BOX",
    "location": [
      "PSA Vault",
      "Collector Crypt (102006143)",
      "900 West Basin Rd",
      "New Castle, DE 19720"
    ],
    "nftAddress": "6sXgUV2wRA7JbbvHiCAwevdrV2japzwti8ChU7Mif2i3",
    "nftCategory": null,
    "nftStatus": "Valid",
    "orientation": "vertical",
    "ownerId": "cm7plxeje0a2d1347u1ctbev0",
    "qualifiers": [],
    "ReasonForRejection": null,
    "serial": "173",
    "status": "Transferred",
    "submissionID": "1",
    "suggestPrice": null,
    "surface": null,
    "type": "Card",
    "updatedAt": "2025-09-06T19:37:47.816Z",
    "vault": "PSA Vault",
    "vaultId": "101835401",
    "year": 2025,
    "set": null,
    "format": null,
    "productCode": null,
    "packCount": null,
    "language": null,
    "platform": null,
    "rating": null,
    "series": null,
    "features": null,
    "publisher": null,
    "nftStandard": null,
    "images": {
      "back": "https://arweave.net/SLH2WYSOQclzWM4Pn97ZeHOMDLJ9gJDBc-i7nTc93tY",
      "backM": "https://d1xpxki1g4htqu.cloudfront.net/5rO5jlOskWiJ98_lBAdQjWfeGy6gAGbB6m1tgbe5KIQ",
      "backS": "https://d1xpxki1g4htqu.cloudfront.net/vmiTtEFK0G3ORi7Iy9D10_llrqk1mSl3f2-PgnzddRs",
      "front": "https://arweave.net/gskpS4cmkm9OsrNAKA0DkqzCHoz1fKqMWpGV3q2Elhc",
      "frontM": "https://d1xpxki1g4htqu.cloudfront.net/Itvh4slECjdvlJv4F8G3d4tkBznzDjanC5qTjtayBBE",
      "frontS": "https://d1xpxki1g4htqu.cloudfront.net/Dr8VydqMgAxgh46g0RXHLm70RdXs011OQAh_4bKIobI"
    },
    "listing": null,
    "offers": [],
    "owner": {
      "id": "cm7plxeje0a2d1347u1ctbev0",
      "name": null,
      "wallet": ""
    }
  },
  {
    "animationUrl": null,
    "authenticated": true,
    "authorId": "clb17jx4r0013mb0jgivpgal4",
    "autographed": false,
    "backImage": "https://arweave.net/R4AQ7IyM4CSRzZ96KAwxy5u4EduNRUXC8HrBusw8It0",
    "blockchain": "Solana",
    "burnId": "cm8za0zse5hh4142fjfh6uvep",
    "category": "Pokemon",
    "centering": null,
    "collectorId": null,
    "corners": null,
    "createdAt": "2025-04-28T22:27:35.954Z",
    "edges": null,
    "frontImage": "https://arweave.net/UDxWsHObs3SceOWn0YbiatSG9WvZHic_q91BfhFtuh8",
    "grade": "MINT 9",
    "gradeNum": 9,
    "gradingCompany": "PSA",
    "gradingID": "71536295",
    "id": "2025042835C16553",
    "insuredValue": "80",
    "itemName": "2006 #5 DEOXYS-HOLO PSA 9 POKEMON EX HOLON PHANTOMS",
    "location": [
      "PSA Vault",
      "Collector Crypt (102006143)",
      "900 West Basin Rd",
      "New Castle, DE 19720"
    ],
    "nftAddress": "G7jsEwiknkA54GDZ2PvEL2DgQXEnAJUs5HQJy8inD3Pz",
    "nftCategory": null,
    "nftStatus": "Valid",
    "orientation": "vertical",
    "ownerId": "cm7plxeje0a2d1347u1ctbev0",
    "qualifiers": [],
    "ReasonForRejection": null,
    "serial": "5",
    "status": "Transferred",
    "submissionID": "1",
    "suggestPrice": null,
    "surface": null,
    "type": "Card",
    "updatedAt": "2025-09-06T19:33:33.425Z",
    "vault": "PSA Vault",
    "vaultId": "101835401",
    "year": 2006,
    "set": null,
    "format": null,
    "productCode": null,
    "packCount": null,
    "language": null,
    "platform": null,
    "rating": null,
    "series": null,
    "features": null,
    "publisher": null,
    "nftStandard": null,
    "images": {
      "back": "https://arweave.net/R4AQ7IyM4CSRzZ96KAwxy5u4EduNRUXC8HrBusw8It0",
      "backM": "https://d1xpxki1g4htqu.cloudfront.net/gayAT8f2MGNfVtB2VPJSx85jwVNlOMsO5YtGEJwgt6Q",
      "backS": "https://d1xpxki1g4htqu.cloudfront.net/sBvsxmS6hA1cflLk1lrKUXgu0d-X_QQA1vkDXqhTF1Y",
      "front": "https://arweave.net/UDxWsHObs3SceOWn0YbiatSG9WvZHic_q91BfhFtuh8",
      "frontM": "https://d1xpxki1g4htqu.cloudfront.net/E2FcovYEkXjpRWdAbOuH3Qf4Ax2kN623lFr9x-hJ9GY",
      "frontS": "https://d1xpxki1g4htqu.cloudfront.net/d3FmRT6inZfbITG4Jon6x1hGaZrUVj6KUjJ9Qp1H-yw"
    },
    "listing": null,
    "offers": [],
    "owner": {
      "id": "cm7plxeje0a2d1347u1ctbev0",
      "name": null,
      "wallet": ""
    }
  },
  {
    "animationUrl": null,
    "authenticated": true,
    "authorId": "clb17jx4r0013mb0jgivpgal4",
    "autographed": false,
    "backImage": "https://arweave.net/fCo61JKmUL-6HcfM9kvzLl-RuphRO4CopIuxrEXhBs0",
    "blockchain": "Solana",
    "burnId": "cm8za0zse5hh4142fjfh6uvep",
    "category": "Pokemon",
    "centering": null,
    "collectorId": null,
    "corners": null,
    "createdAt": "2025-04-28T22:27:35.259Z",
    "edges": null,
    "frontImage": "https://arweave.net/AdcxVuUxTpgPd9pL_fXxDUte-jA-EtyNpEmhEJrSnek",
    "grade": "VG-EX 4",
    "gradeNum": 4,
    "gradingCompany": "PSA",
    "gradingID": "91842894",
    "id": "2025042835C16552",
    "insuredValue": "72",
    "itemName": "2002 #46 HAUNTER-REVERSE FOIL PSA 4 POKEMON LEGENDARY COLLECTION",
    "location": [
      "PSA Vault",
      "Collector Crypt (102006143)",
      "900 West Basin Rd",
      "New Castle, DE 19720"
    ],
    "nftAddress": "4Ge9q4APqCbwNu1C1PnoqeeHpEwy3SHGiCEswg5wGWd6",
    "nftCategory": null,
    "nftStatus": "Valid",
    "orientation": "vertical",
    "ownerId": "cm7plxeje0a2d1347u1ctbev0",
    "qualifiers": [],
    "ReasonForRejection": null,
    "serial": "46",
    "status": "Transferred",
    "submissionID": "1",
    "suggestPrice": null,
    "surface": null,
    "type": "Card",
    "updatedAt": "2025-09-06T19:37:53.235Z",
    "vault": "PSA Vault",
    "vaultId": "101835401",
    "year": 2002,
    "set": null,
    "format": null,
    "productCode": null,
    "packCount": null,
    "language": null,
    "platform": null,
    "rating": null,
    "series": null,
    "features": null,
    "publisher": null,
    "nftStandard": null,
    "images": {
      "back": "https://arweave.net/fCo61JKmUL-6HcfM9kvzLl-RuphRO4CopIuxrEXhBs0",
      "backM": "https://d1xpxki1g4htqu.cloudfront.net/oKx9YsZDN9Z30dws7SiUolJr6ZCGLcE0eGRopeC09y4",
      "backS": "https://d1xpxki1g4htqu.cloudfront.net/t4S-5jnl62Q6dnAHYSo1NpG7-iykyAfDy09VtSTiFpg",
      "front": "https://arweave.net/AdcxVuUxTpgPd9pL_fXxDUte-jA-EtyNpEmhEJrSnek",
      "frontM": "https://d1xpxki1g4htqu.cloudfront.net/Rpc-Kq4utkdqMqM3JgTYSoIZv31fgUgxmu2C_1geqQY",
      "frontS": "https://d1xpxki1g4htqu.cloudfront.net/t86gNnkhzzbvkEjKRR-GTOPc58LarC8L0i39XB0lxRE"
    },
    "listing": null,
    "offers": [],
    "owner": {
      "id": "cm7plxeje0a2d1347u1ctbev0",
      "name": null,
      "wallet": ""
    }
  },
  {
    "animationUrl": null,
    "authenticated": true,
    "authorId": "clb17jx4r0013mb0jgivpgal4",
    "autographed": false,
    "backImage": "https://arweave.net/Nt6QrXiaZbJwYkjrn6viaw0pw-faBIXHG2FRDTBGDAg",
    "blockchain": "Solana",
    "burnId": "cm8za0zse5hh4142fjfh6uvep",
    "category": "Pokemon",
    "centering": null,
    "collectorId": null,
    "corners": null,
    "createdAt": "2025-04-28T22:27:33.910Z",
    "edges": null,
    "frontImage": "https://arweave.net/Klp3KifsYHlGJLnaep2X88IEF9wDrMx_n8qZX7EnBWI",
    "grade": "GEM-MT 10",
    "gradeNum": 10,
    "gradingCompany": "PSA",
    "gradingID": "102868257",
    "id": "2025042833C16550",
    "insuredValue": "70",
    "itemName": "2023 #071 LUXRAY PSA 10 POKEMON PAL EN-PALDEA EVOLVED | COSMOS EXCLUSIVE",
    "location": [
      "PSA Vault",
      "Collector Crypt (102006143)",
      "900 West Basin Rd",
      "New Castle, DE 19720"
    ],
    "nftAddress": "5FKE3MD5TaRXbsouEHYP8Mp67Sf1kRYRR9EY1cuj8sT",
    "nftCategory": null,
    "nftStatus": "Valid",
    "orientation": "vertical",
    "ownerId": "cm7plxeje0a2d1347u1ctbev0",
    "qualifiers": [],
    "ReasonForRejection": null,
    "serial": "071",
    "status": "Transferred",
    "submissionID": "1",
    "suggestPrice": null,
    "surface": null,
    "type": "Card",
    "updatedAt": "2025-09-06T19:36:19.195Z",
    "vault": "PSA Vault",
    "vaultId": "101835401",
    "year": 2023,
    "set": null,
    "format": null,
    "productCode": null,
    "packCount": null,
    "language": null,
    "platform": null,
    "rating": null,
    "series": null,
    "features": null,
    "publisher": null,
    "nftStandard": null,
    "images": {
      "back": "https://arweave.net/Nt6QrXiaZbJwYkjrn6viaw0pw-faBIXHG2FRDTBGDAg",
      "backM": "https://d1xpxki1g4htqu.cloudfront.net/hqrOUjT60O4G46qDc5BrcsozaVV50yGosDF1DlmDf28",
      "backS": "https://d1xpxki1g4htqu.cloudfront.net/MSaEixj3BKNBSByS1k64mT2_vuOrkPp2ESl44MgTvFI",
      "front": "https://arweave.net/Klp3KifsYHlGJLnaep2X88IEF9wDrMx_n8qZX7EnBWI",
      "frontM": "https://d1xpxki1g4htqu.cloudfront.net/a0lOkkC28bqVt9Ix8iTWnQAZgRq34kJNYRm-yfdEzE8",
      "frontS": "https://d1xpxki1g4htqu.cloudfront.net/hlIS44UnivM1Gl4mi-vpgxrxWDNo93ibJzLrzoJoYXs"
    },
    "listing": null,
    "offers": [],
    "owner": {
      "id": "cm7plxeje0a2d1347u1ctbev0",
      "name": null,
      "wallet": ""
    }
  },
  {
    "animationUrl": null,
    "authenticated": true,
    "authorId": "clb17jx4r0013mb0jgivpgal4",
    "autographed": false,
    "backImage": "https://arweave.net/Zb05N38uyLtztSFe3N-ekYkuM56U49k-arEEPOi_Zik",
    "blockchain": "Solana",
    "burnId": "cm8za0zse5hh4142fjfh6uvep",
    "category": "Pokemon",
    "centering": null,
    "collectorId": null,
    "corners": null,
    "createdAt": "2025-04-28T22:27:33.227Z",
    "edges": null,
    "frontImage": "https://arweave.net/UqjSrTfH8Icj1W_r-6nrY2QxTVyP5SM07lzIrXdSY-I",
    "grade": "MINT 9",
    "gradeNum": 9,
    "gradingCompany": "PSA",
    "gradingID": "104130553",
    "id": "2025042833C16549",
    "insuredValue": "67",
    "itemName": "2000 #243 RAIKOU-HOLO PSA 9 POKEMON JAPANESE NEO 3",
    "location": [
      "PSA Vault",
      "Collector Crypt (102006143)",
      "900 West Basin Rd",
      "New Castle, DE 19720"
    ],
    "nftAddress": "GLprgwLQ9a2MqKx2BgpyBz8DP9HB6zEBwqE6paiD7Hc7",
    "nftCategory": null,
    "nftStatus": "Valid",
    "orientation": "vertical",
    "ownerId": "cm7plxeje0a2d1347u1ctbev0",
    "qualifiers": [],
    "ReasonForRejection": null,
    "serial": "243",
    "status": "Transferred",
    "submissionID": "1",
    "suggestPrice": null,
    "surface": null,
    "type": "Card",
    "updatedAt": "2025-09-06T19:30:13.872Z",
    "vault": "PSA Vault",
    "vaultId": "101835401",
    "year": 2000,
    "set": null,
    "format": null,
    "productCode": null,
    "packCount": null,
    "language": null,
    "platform": null,
    "rating": null,
    "series": null,
    "features": null,
    "publisher": null,
    "nftStandard": null,
    "images": {
      "back": "https://arweave.net/Zb05N38uyLtztSFe3N-ekYkuM56U49k-arEEPOi_Zik",
      "backM": "https://d1xpxki1g4htqu.cloudfront.net/yokd08Rk0kqAkxq4v0lYfytz4830wBTOHi-PVxTH_0g",
      "backS": "https://d1xpxki1g4htqu.cloudfront.net/5N-VPtQ4nAjb80GXmxR7452l21WYopUk1iulQGXQdbc",
      "front": "https://arweave.net/UqjSrTfH8Icj1W_r-6nrY2QxTVyP5SM07lzIrXdSY-I",
      "frontM": "https://d1xpxki1g4htqu.cloudfront.net/nABOFojXUx7sqqUhYENOuNY1a8a3VRvGMOZaUoQQ0x8",
      "frontS": "https://d1xpxki1g4htqu.cloudfront.net/canusJbFb1O1dJ_qJu7o_fWW3fU2Es99Lra5VSYCFzM"
    },
    "listing": null,
    "offers": [],
    "owner": {
      "id": "cm7plxeje0a2d1347u1ctbev0",
      "name": null,
      "wallet": ""
    }
  },
  {
    "animationUrl": null,
    "authenticated": true,
    "authorId": "clb17jx4r0013mb0jgivpgal4",
    "autographed": false,
    "backImage": "https://arweave.net/vgT6Jek2NW30qf2XobKbLhP1uIpOUWY-VXX-1SbVI7w",
    "blockchain": "Solana",
    "burnId": "cm9w4asgm21wkwuhzgo4ig4y0",
    "category": "Pokemon",
    "centering": null,
    "collectorId": null,
    "corners": null,
    "createdAt": "2025-04-28T22:27:32.356Z",
    "edges": null,
    "frontImage": "https://arweave.net/Mzk3sVq2bnj8717lF62zKwGjJQvmzhBV9vhwwv1ZOsA",
    "grade": "MINT 9",
    "gradeNum": 9,
    "gradingCompany": "PSA",
    "gradingID": "102234555",
    "id": "2025042832C16548",
    "insuredValue": "67",
    "itemName": "2005 #6 KYOGRE-HOLO PSA 9 POKEMON EX EMERALD",
    "location": [
      "PSA Vault",
      "Collector Crypt (102006143)",
      "900 West Basin Rd",
      "New Castle, DE 19720"
    ],
    "nftAddress": "7XBPy9cLusGwYXvryH14JfTHx9BFifYmDy8vSvhaT1ua",
    "nftCategory": null,
    "nftStatus": "Valid",
    "orientation": "vertical",
    "ownerId": "cm7plxeje0a2d1347u1ctbev0",
    "qualifiers": [],
    "ReasonForRejection": null,
    "serial": "6",
    "status": "Transferred",
    "submissionID": "1",
    "suggestPrice": null,
    "surface": null,
    "type": "Card",
    "updatedAt": "2025-09-06T19:41:04.058Z",
    "vault": "PSA Vault",
    "vaultId": "101835401",
    "year": 2005,
    "set": null,
    "format": null,
    "productCode": null,
    "packCount": null,
    "language": null,
    "platform": null,
    "rating": null,
    "series": null,
    "features": null,
    "publisher": null,
    "nftStandard": null,
    "images": {
      "back": "https://arweave.net/vgT6Jek2NW30qf2XobKbLhP1uIpOUWY-VXX-1SbVI7w",
      "backM": "https://d1xpxki1g4htqu.cloudfront.net/Sax-Ra3JvZXgkCFWV5ID976kn67ko6BFTtwz9xyd1WM",
      "backS": "https://d1xpxki1g4htqu.cloudfront.net/rznVEolUv0Pi0GzHhJZa7WBjkScwYkyKkFzZHmrzvBU",
      "front": "https://arweave.net/Mzk3sVq2bnj8717lF62zKwGjJQvmzhBV9vhwwv1ZOsA",
      "frontM": "https://d1xpxki1g4htqu.cloudfront.net/cuHkBNIQt87bXLUujfGyYrQXWn3n_pUnjkCw9Z1SHYo",
      "frontS": "https://d1xpxki1g4htqu.cloudfront.net/d62b9Pg4-FWeqc4AVpN2tZuE9IYu6peR9rxmuGub5Ak"
    },
    "listing": null,
    "offers": [],
    "owner": {
      "id": "cm7plxeje0a2d1347u1ctbev0",
      "name": null,
      "wallet": ""
    }
  },
  {
    "animationUrl": null,
    "authenticated": true,
    "authorId": "clb17jx4r0013mb0jgivpgal4",
    "autographed": false,
    "backImage": "https://arweave.net/e-zJgfDSlrIp3I8GyyqX0QugKLQQHGmJEuIEohtV4uk",
    "blockchain": "Solana",
    "burnId": "cm8za0zse5hh4142fjfh6uvep",
    "category": "Pokemon",
    "centering": null,
    "collectorId": null,
    "corners": null,
    "createdAt": "2025-04-28T22:27:30.660Z",
    "edges": null,
    "frontImage": "https://arweave.net/IlarzBSGZ5Z1QJAEp_Xwu9G-tgxF40iphPpuPoxcv3M",
    "grade": "NM-MT 8",
    "gradeNum": 8,
    "gradingCompany": "PSA",
    "gradingID": "97695314",
    "id": "2025042830C16546",
    "insuredValue": "65",
    "itemName": "2005 #9 RAYQUAZA-HOLO PSA 8 POKEMON EX EMERALD",
    "location": [
      "PSA Vault",
      "Collector Crypt (102006143)",
      "900 West Basin Rd",
      "New Castle, DE 19720"
    ],
    "nftAddress": "77Eu2So3ZpZe5KdkzywKjAyeVHP99uPW95QPmg6pa6Br",
    "nftCategory": null,
    "nftStatus": "Valid",
    "orientation": "vertical",
    "ownerId": "cm7plxeje0a2d1347u1ctbev0",
    "qualifiers": [],
    "ReasonForRejection": null,
    "serial": "9",
    "status": "Transferred",
    "submissionID": "1",
    "suggestPrice": null,
    "surface": null,
    "type": "Card",
    "updatedAt": "2025-09-06T19:30:10.479Z",
    "vault": "PSA Vault",
    "vaultId": "101835401",
    "year": 2005,
    "set": null,
    "format": null,
    "productCode": null,
    "packCount": null,
    "language": null,
    "platform": null,
    "rating": null,
    "series": null,
    "features": null,
    "publisher": null,
    "nftStandard": null,
    "images": {
      "back": "https://arweave.net/e-zJgfDSlrIp3I8GyyqX0QugKLQQHGmJEuIEohtV4uk",
      "backM": "https://d1xpxki1g4htqu.cloudfront.net/DlVH7PtDJfoaJImFUiGj12VczFk4mH6WX6N-lFkOTc0",
      "backS": "https://d1xpxki1g4htqu.cloudfront.net/arEr0K2EjACailA_WY8WJB2glDZ0upbd32Cxco7y7Sw",
      "front": "https://arweave.net/IlarzBSGZ5Z1QJAEp_Xwu9G-tgxF40iphPpuPoxcv3M",
      "frontM": "https://d1xpxki1g4htqu.cloudfront.net/MOrzBsDAYDQ49BnweCCUf__6nJn91O8NljDGDphj_00",
      "frontS": "https://d1xpxki1g4htqu.cloudfront.net/9o1jDsuQ90n49MMZzAhbroJwo8t65oD6jo5vBFTv9oA"
    },
    "listing": null,
    "offers": [],
    "owner": {
      "id": "cm7plxeje0a2d1347u1ctbev0",
      "name": null,
      "wallet": ""
    }
  }
]