[
  {
    "animationUrl": null,
    "authenticated": true,
    "authorId": "clb17jx4r0013mb0jgivpgal4",
    "autographed": false,
    "backImage": "https://arweave.net/c-HOMmv8naI-5OR421JORtTkMDimzHlcSz4wQl8A7R8",
    "blockchain": "Solana",
    "burnId": "cmad9lzqi0ilp6hoajo6wel6x",
    "category": "Pokemon",
    "centering": null,
    "collectorId": null,
    "corners": null,
    "createdAt": "2025-05-20T17:15:58.493Z",
    "edges": null,
    "frontImage": "https://arweave.net/F9xqFbyWJZ4ZJQtJEvx_B_MxjojThBp8GfUMpxtQFYg",
    "grade": "GEM-MT 10",
    "gradeNum": 10,
    "gradingCompany": "PSA",
    "gradingID": "108288132",
    "id": "2025052058C19860",
    "insuredValue": "130",
    "itemName": "2023 #98 DETECTIVE PIKACHU 2023 PSA 10 JAPANESE SV-P PROMO POKEMON",
    "location": [
      "PSA Vault",
      "Collector Crypt (102006143)",
      "900 West Basin Rd",
      "New Castle, DE 19720"
    ],
    "nftAddress": "6NKmn7BBim95GHpbTwJuKsF4THuKL6iwrA9Uj1MATaPC",
    "nftCategory": null,
    "nftStatus": "Valid",
    "orientation": "vertical",
    "ownerId": "cm7plxeje0a2d1347u1ctbev0",
    "qualifiers": [],
    "ReasonForRejection": null,
    "serial": "98",
    "status": "Transferred",
    "submissionID": "1",
    "suggestPrice": null,
    "surface": null,
    "type": "Card",
    "updatedAt": "2025-09-06T19:43:21.642Z",
    "vault": "PSA Vault",
    "vaultId": "171171588",
    "year": 2023,
    "set": null,
    "format": null,
    "productCode": null,
    "packCount": null,
    "language": null,
    "platform": null,
    "rating": null,
    "series": null,
    "features": null,
    "publisher": null,
    "nftStandard": null,
    "images": {
      "back": "https://arweave.net/c-HOMmv8naI-5OR421JORtTkMDimzHlcSz4wQl8A7R8",
      "backM": "https://d1xpxki1g4htqu.cloudfront.net/tBMSRmbgkwAWFmPXaOAcs-qwqIaV1l3_nBzuN2OoLwU",
      "backS": "https://d1xpxki1g4htqu.cloudfront.net/HSAzukOnY59XZFrGoEsf9PWn78Mgig_Ci2ApSt0Wvy8",
      "front": "https://arweave.net/F9xqFbyWJZ4ZJQtJEvx_B_MxjojThBp8GfUMpxtQFYg",
      "frontM": "https://d1xpxki1g4htqu.cloudfront.net/vbfbMjhQr41B3o_FlO-M3vFHdJy7CCt7J5VRRBrmA-g",
      "frontS": "https://d1xpxki1g4htqu.cloudfront.net/Zuledr2f-GQ7YM9itIe3_J-4z3UQ44O48OZFpXAigSo"
    },
    "listing": null,
    "offers": [],
    "owner": {
      "id": "cm7plxeje0a2d1347u1ctbev0",
      "name": null,
      "wallet": ""
    }
  },
  {
    "animationUrl": null,
    "authenticated": true,
    "authorId": "clb17jx4r0013mb0jgivpgal4",
    "autographed": false,
    "backImage": "https://arweave.net/5CFnSU1hmo9qjFGa3pKr4k1FiT_K2dQDILABpHu1K30",
    "blockchain": "Solana",
    "burnId": "cm9yts9tl2qr2wuhz1ezqvfw4",
    "category": "Pokemon",
    "centering": null,
    "collectorId": null,
    "corners": null,
    "createdAt": "2025-05-20T17:15:56.562Z",
    "edges": null,
    "frontImage": "https://arweave.net/WDJ1c-pw7jA_-4miB9KSD4pkxIQ8f9wrRTfeE9LAUk0",
    "grade": "GEM-MT 10",
    "gradeNum": 10,
    "gradingCompany": "PSA",
    "gradingID": "108372393",
    "id": "2025052056C19858",
    "insuredValue": "125",
    "itemName": "2024 #211 ESPEON EX 2024 PSA 10 JAPANESE SV8a-TERASTAL FEST ex POKEMON",
    "location": [
      "PSA Vault",
      "Collector Crypt (102006143)",
      "900 West Basin Rd",
      "New Castle, DE 19720"
    ],
    "nftAddress": "BGxVaQRd44ehmG8pKfgBE4QwcXo6c9vE15uXhKFTkBAm",
    "nftCategory": null,
    "nftStatus": "Valid",
    "orientation": "vertical",
    "ownerId": "cm7plxeje0a2d1347u1ctbev0",
    "qualifiers": [],
    "ReasonForRejection": null,
    "serial": "211",
    "status": "Transferred",
    "submissionID": "1",
    "suggestPrice": null,
    "surface": null,
    "type": "Card",
    "updatedAt": "2025-09-06T19:44:17.129Z",
    "vault": "PSA Vault",
    "vaultId": "171171593",
    "year": 2024,
    "set": null,
    "format": null,
    "productCode": null,
    "packCount": null,
    "language": null,
    "platform": null,
    "rating": null,
    "series": null,
    "features": null,
    "publisher": null,
    "nftStandard": null,
    "images": {
      "back": "https://arweave.net/5CFnSU1hmo9qjFGa3pKr4k1FiT_K2dQDILABpHu1K30",
      "backM": "https://d1xpxki1g4htqu.cloudfront.net/gnkOxz-xPO1sFsuSY3GEpTzAYzr8WrA7WHrODbjj57s",
      "backS": "https://d1xpxki1g4htqu.cloudfront.net/5rSRplaFweQ5bt92tYvueyLYtktnCLZM4CvnCD3Ro5E",
      "front": "https://arweave.net/WDJ1c-pw7jA_-4miB9KSD4pkxIQ8f9wrRTfeE9LAUk0",
      "frontM": "https://d1xpxki1g4htqu.cloudfront.net/o0xjf8kDtuKk8Ak2xHg57a7irMLPE-492ziHIUKEXSQ",
      "frontS": "https://d1xpxki1g4htqu.cloudfront.net/nk1zQGuebti_UsOYspSYxIuSg3Soq5HUJqRqIbTBSzg"
    },
    "listing": null,
    "offers": [],
    "owner": {
      "id": "cm7plxeje0a2d1347u1ctbev0",
      "name": null,
      "wallet": ""
    }
  },
  {
    "animationUrl": null,
    "authenticated": true,
    "authorId": "clb17jx4r0013mb0jgivpgal4",
    "autographed": false,
    "backImage": "https://arweave.net/oVTmMIke5YUi4MzXTjuulJM53NbK-WMj5aOHrYG2qMM",
    "blockchain": "Solana",
    "burnId": "cmavknibw5ha86hoa3poxkq6e",
    "category": "Pokemon",
    "centering": null,
    "collectorId": null,
    "corners": null,
    "createdAt": "2025-05-20T17:15:54.986Z",
    "edges": null,
    "frontImage": "https://arweave.net/T6gmnH-mOCRHjOBu710tPDZpy6qM1gbagh1YjQwKOLk",
    "grade": "MINT 9",
    "gradeNum": 9,
    "gradingCompany": "PSA",
    "gradingID": "108244034",
    "id": "2025052054C19857",
    "insuredValue": "260",
    "itemName": "2021 #209 FULL ART/GLACEON VMAX 2021 PSA 9 SWORD & SHIELD EVOLVING SKIES POKEMON",
    "location": [
      "PSA Vault",
      "Collector Crypt (102006143)",
      "900 West Basin Rd",
      "New Castle, DE 19720"
    ],
    "nftAddress": "49aaY3UyhWBW2vJ5SRixYevjFKzS4jqBca2mUTjehxcY",
    "nftCategory": null,
    "nftStatus": "Valid",
    "orientation": "vertical",
    "ownerId": "cmavknibw5ha76hoazobhp7p6",
    "qualifiers": [],
    "ReasonForRejection": null,
    "serial": "209",
    "status": "Transferred",
    "submissionID": "1",
    "suggestPrice": null,
    "surface": null,
    "type": "Card",
    "updatedAt": "2025-09-06T19:44:44.841Z",
    "vault": "PSA Vault",
    "vaultId": "171171609",
    "year": 2021,
    "set": null,
    "format": null,
    "productCode": null,
    "packCount": null,
    "language": null,
    "platform": null,
    "rating": null,
    "series": null,
    "features": null,
    "publisher": null,
    "nftStandard": null,
    "images": {
      "back": "https://arweave.net/oVTmMIke5YUi4MzXTjuulJM53NbK-WMj5aOHrYG2qMM",
      "backM": "https://d1xpxki1g4htqu.cloudfront.net/3-MHSdx_u8n_sBwaVHVZHaiFpxXQTIN7ib8ByMXuUfI",
      "backS": "https://d1xpxki1g4htqu.cloudfront.net/1Js4g0-vGpagRcKlj3N0xcEfMW0UVmMJAyNKFLuufBo",
      "front": "https://arweave.net/T6gmnH-mOCRHjOBu710tPDZpy6qM1gbagh1YjQwKOLk",
      "frontM": "https://d1xpxki1g4htqu.cloudfront.net/twmePcq7qfL5nQknt1P_OagM75gaXQwnEmERHggswEY",
      "frontS": "https://d1xpxki1g4htqu.cloudfront.net/yjZ9rVbKaQ_xfasNFPmOfHLN4yjff_J2Ez97KqPe84E"
    },
    "listing": null,
    "offers": [],
    "owner": {
      "id": "cmavknibw5ha76hoazobhp7p6",
      "name": "HST ",
      "wallet": "87qUVbmyHK8ahV6ASWcD5knLtHFNGD26XE2HCN83uvT3"
    }
  },
  {
    "animationUrl": null,
    "authenticated": true,
    "authorId": "clb17jx4r0013mb0jgivpgal4",
    "autographed": false,
    "backImage": "https://arweave.net/JiL6II6yAvvWl_uwl3Bj75CX3FRJ1Zlbva5ZpYLz7P4",
    "blockchain": "Solana",
    "burnId": "cm9w4asgm21wkwuhzgo4ig4y0",
    "category": "Pokemon",
    "centering": null,
    "collectorId": null,
    "corners": null,
    "createdAt": "2025-05-20T17:15:53.997Z",
    "edges": null,
    "frontImage": "https://arweave.net/WbPfgi61JOp7uf0EJOgRTEzy6ilj9PbD-LLxDZZJpkY",
    "grade": "MINT 9",
    "gradeNum": 9,
    "gradingCompany": "PSA",
    "gradingID": "107960071",
    "id": "2025052053C19856",
    "insuredValue": "320",
    "itemName": "2002 #10 PIKACHU-HOLO 2002 PSA 9 JAPANESE McDONALD'S POKEMON",
    "location": [
      "PSA Vault",
      "Collector Crypt (102006143)",
      "900 West Basin Rd",
      "New Castle, DE 19720"
    ],
    "nftAddress": "HxcLnAx6QVk1BDrMRub3drWVprjyP6QTt717QtZonut9",
    "nftCategory": null,
    "nftStatus": "Valid",
    "orientation": "vertical",
    "ownerId": "cm7plxeje0a2d1347u1ctbev0",
    "qualifiers": [],
    "ReasonForRejection": null,
    "serial": "10",
    "status": "Transferred",
    "submissionID": "1",
    "suggestPrice": null,
    "surface": null,
    "type": "Card",
    "updatedAt": "2025-09-06T19:15:56.535Z",
    "vault": "PSA Vault",
    "vaultId": "171171596",
    "year": 2002,
    "set": null,
    "format": null,
    "productCode": null,
    "packCount": null,
    "language": null,
    "platform": null,
    "rating": null,
    "series": null,
    "features": null,
    "publisher": null,
    "nftStandard": null,
    "images": {
      "back": "https://arweave.net/JiL6II6yAvvWl_uwl3Bj75CX3FRJ1Zlbva5ZpYLz7P4",
      "backM": "https://d1xpxki1g4htqu.cloudfront.net/OXdkdVqQ4b-GytzZS6CFHZ5kva09y3uzvLqLq2IP44w",
      "backS": "https://d1xpxki1g4htqu.cloudfront.net/JeIy17G4VTE_pkRrUgTgQy12HvOmL0vABz_t9V1UXHc",
      "front": "https://arweave.net/WbPfgi61JOp7uf0EJOgRTEzy6ilj9PbD-LLxDZZJpkY",
      "frontM": "https://d1xpxki1g4htqu.cloudfront.net/SVFBVgGLgKJ6eib2A1-cLl4SgxmvtKbAeR3VT1ONXTc",
      "frontS": "https://d1xpxki1g4htqu.cloudfront.net/fdW0VhdsdPxpKrR4jAbx_tWxudDhuKeXYY-51-HhGAg"
    },
    "listing": null,
    "offers": [],
    "owner": {
      "id": "cm7plxeje0a2d1347u1ctbev0",
      "name": null,
      "wallet": ""
    }
  },
  {
    "animationUrl": null,
    "authenticated": true,
    "authorId": "clb17jx4r0013mb0jgivpgal4",
    "autographed": false,
    "backImage": "https://arweave.net/9MQE73Y2kdosQXnVJ5QgI1TgDOXTnoNhWOXZABgKIwI",
    "blockchain": "Solana",
    "burnId": "cmagcz5cr1iag6hoa32eauafx",
    "category": "Pokemon",
    "centering": null,
    "collectorId": null,
    "corners": null,
    "createdAt": "2025-05-20T17:15:48.224Z",
    "edges": null,
    "frontImage": "https://arweave.net/Lr63ZbNBr1G1Ecp6XRCfkf2xxat1StRZV7lpUoRO9vE",
    "grade": "GEM-MT 10",
    "gradeNum": 10,
    "gradingCompany": "PSA",
    "gradingID": "107113065",
    "id": "2025052048C19850",
    "insuredValue": "130",
    "itemName": "2023 #98 DETECTIVE PIKACHU 2023 PSA 10 JAPANESE SV-P PROMO POKEMON",
    "location": [
      "PSA Vault",
      "Collector Crypt (102006143)",
      "900 West Basin Rd",
      "New Castle, DE 19720"
    ],
    "nftAddress": "6suD2ZDJTMFzDhfGYBhEcZexMi2GL7J8t33WdquZU5YB",
    "nftCategory": null,
    "nftStatus": "Valid",
    "orientation": "vertical",
    "ownerId": "cm7plxeje0a2d1347u1ctbev0",
    "qualifiers": [],
    "ReasonForRejection": null,
    "serial": "98",
    "status": "Transferred",
    "submissionID": "1",
    "suggestPrice": null,
    "surface": null,
    "type": "Card",
    "updatedAt": "2025-09-06T19:35:11.864Z",
    "vault": "PSA Vault",
    "vaultId": "171171594",
    "year": 2023,
    "set": null,
    "format": null,
    "productCode": null,
    "packCount": null,
    "language": null,
    "platform": null,
    "rating": null,
    "series": null,
    "features": null,
    "publisher": null,
    "nftStandard": null,
    "images": {
      "back": "https://arweave.net/9MQE73Y2kdosQXnVJ5QgI1TgDOXTnoNhWOXZABgKIwI",
      "backM": "https://d1xpxki1g4htqu.cloudfront.net/czzZZwNnwe-Qjf-WzC97jhAXEP1972gxhHP_a_CXI6c",
      "backS": "https://d1xpxki1g4htqu.cloudfront.net/mt-loqvCCqWrbsYw0kwWt6foZwl6NehWxDMg5dDkQMg",
      "front": "https://arweave.net/Lr63ZbNBr1G1Ecp6XRCfkf2xxat1StRZV7lpUoRO9vE",
      "frontM": "https://d1xpxki1g4htqu.cloudfront.net/x0_6V5uwgz68O9G84sfOkAiBUDq-tMemANPdOdPADEk",
      "frontS": "https://d1xpxki1g4htqu.cloudfront.net/LRxkaxEyplvSBjt3PwSdjvEYDRUNlEl9MOwbUVVSUR8"
    },
    "listing": null,
    "offers": [],
    "owner": {
      "id": "cm7plxeje0a2d1347u1ctbev0",
      "name": null,
      "wallet": ""
    }
  },
  {
    "animationUrl": null,
    "authenticated": true,
    "authorId": "clb17jx4r0013mb0jgivpgal4",
    "autographed": false,
    "backImage": "https://arweave.net/KupWHc18a-VqU5AlaFtAElIhT-HtnKmlTyi_cTY7mFY",
    "blockchain": "Solana",
    "burnId": "cmawzqt8b09voryj2579yf1n1",
    "category": "Pokemon",
    "centering": null,
    "collectorId": null,
    "corners": null,
    "createdAt": "2025-05-20T17:15:46.261Z",
    "edges": null,
    "frontImage": "https://arweave.net/eUzbMqW_bmbdSx9AyeFlhjOWPc-B7XjbnYJqLdVR-dk",
    "grade": "GEM-MT 10",
    "gradeNum": 10,
    "gradingCompany": "PSA",
    "gradingID": "103157250",
    "id": "2025052046C19848",
    "insuredValue": "140",
    "itemName": "2024 #205 WALKING WAKE EX 2024 PSA 10 TEF EN-TEMPORAL FORCES POKEMON",
    "location": [
      "PSA Vault",
      "Collector Crypt (102006143)",
      "900 West Basin Rd",
      "New Castle, DE 19720"
    ],
    "nftAddress": "9f9YMuQhARhUoZRs4pqLctsGLisrdPVsq3XjCQoDxTPv",
    "nftCategory": null,
    "nftStatus": "Valid",
    "orientation": "vertical",
    "ownerId": "cm7plxeje0a2d1347u1ctbev0",
    "qualifiers": [],
    "ReasonForRejection": null,
    "serial": "205",
    "status": "Transferred",
    "submissionID": "1",
    "suggestPrice": null,
    "surface": null,
    "type": "Card",
    "updatedAt": "2025-09-06T19:44:55.212Z",
    "vault": "PSA Vault",
    "vaultId": "171178738",
    "year": 2024,
    "set": null,
    "format": null,
    "productCode": null,
    "packCount": null,
    "language": null,
    "platform": null,
    "rating": null,
    "series": null,
    "features": null,
    "publisher": null,
    "nftStandard": null,
    "images": {
      "back": "https://arweave.net/KupWHc18a-VqU5AlaFtAElIhT-HtnKmlTyi_cTY7mFY",
      "backM": "https://d1xpxki1g4htqu.cloudfront.net/6BJje6onaWVl2v_vzwZnWaKgxZAMfl1obtw4JuHcYsk",
      "backS": "https://d1xpxki1g4htqu.cloudfront.net/CnbRqfgPT9XnjWAbeb1xwc53Jo7ClfpbF2mdDRxTdiA",
      "front": "https://arweave.net/eUzbMqW_bmbdSx9AyeFlhjOWPc-B7XjbnYJqLdVR-dk",
      "frontM": "https://d1xpxki1g4htqu.cloudfront.net/LhJcNy16CyXHUxCq8CXkYjus1J6v5aFLwHYyMJvEW5U",
      "frontS": "https://d1xpxki1g4htqu.cloudfront.net/ngPtM8im8KsQ1KrgXMjVixj3pgI4T2XLzxjPF9uDEGs"
    },
    "listing": null,
    "offers": [],
    "owner": {
      "id": "cm7plxeje0a2d1347u1ctbev0",
      "name": null,
      "wallet": ""
    }
  },
  {
    "animationUrl": null,
    "authenticated": true,
    "authorId": "clb17jx4r0013mb0jgivpgal4",
    "autographed": false,
    "backImage": "https://arweave.net/B8DrV43CimZLJSZxtBdclVwZyV3SQJtzef1SBrifaqI",
    "blockchain": "Solana",
    "burnId": "cm7l4eae809w666u9fbc0ynpk",
    "category": "Pokemon",
    "centering": null,
    "collectorId": null,
    "corners": null,
    "createdAt": "2025-05-20T17:15:43.683Z",
    "edges": null,
    "frontImage": "https://arweave.net/323DeBEB7j34Ef3ChmkQpIFZ-y3d5XQ0YO18kz8eQCA",
    "grade": "GEM-MT 10",
    "gradeNum": 10,
    "gradingCompany": "PSA",
    "gradingID": "101827230",
    "id": "2025052043C19845",
    "insuredValue": "115",
    "itemName": "2023 #GG35 FULL ART/LEAFEON VSTAR 2023 PSA 10 SWORD AND SHIELD CROWN ZENITH POKEMON",
    "location": [
      "PSA Vault",
      "Collector Crypt (102006143)",
      "900 West Basin Rd",
      "New Castle, DE 19720"
    ],
    "nftAddress": "GnMWY96vCXpNiNBVRjqBEnDm5cLt9EucStyVmkQAWC41",
    "nftCategory": null,
    "nftStatus": "Valid",
    "orientation": "vertical",
    "ownerId": "cm7plxeje0a2d1347u1ctbev0",
    "qualifiers": [],
    "ReasonForRejection": null,
    "serial": "GG35",
    "status": "Transferred",
    "submissionID": "1",
    "suggestPrice": null,
    "surface": null,
    "type": "Card",
    "updatedAt": "2025-09-06T19:44:10.152Z",
    "vault": "PSA Vault",
    "vaultId": "171171604",
    "year": 2023,
    "set": null,
    "format": null,
    "productCode": null,
    "packCount": null,
    "language": null,
    "platform": null,
    "rating": null,
    "series": null,
    "features": null,
    "publisher": null,
    "nftStandard": null,
    "images": {
      "back": "https://arweave.net/B8DrV43CimZLJSZxtBdclVwZyV3SQJtzef1SBrifaqI",
      "backM": "https://d1xpxki1g4htqu.cloudfront.net/hnbcLufUP9aeSjwW633pZSkznvkrnarQfNkTqrkVkaE",
      "backS": "https://d1xpxki1g4htqu.cloudfront.net/gOlSqZkjObOzKmYiDnDlSHoXTA6LVDeTse3az7VjnII",
      "front": "https://arweave.net/323DeBEB7j34Ef3ChmkQpIFZ-y3d5XQ0YO18kz8eQCA",
      "frontM": "https://d1xpxki1g4htqu.cloudfront.net/HNQSWt5fuKN7WSwjYXYg27uLXZjvvb-tkRmcEd096tQ",
      "frontS": "https://d1xpxki1g4htqu.cloudfront.net/HaLbznislAjtfcPFBiufiMvAAEtguevMgcMxl2w7qRU"
    },
    "listing": null,
    "offers": [],
    "owner": {
      "id": "cm7plxeje0a2d1347u1ctbev0",
      "name": null,
      "wallet": ""
    }
  },
  {
    "animationUrl": null,
    "authenticated": true,
    "authorId": "clb17jx4r0013mb0jgivpgal4",
    "autographed": false,
    "backImage": "https://arweave.net/WkdQVc2V5b40CcGk5HbrXClMnH2xt0l-Vk3h4foKucE",
    "blockchain": "Solana",
    "burnId": "cmagcz5cr1iag6hoa32eauafx",
    "category": "Pokemon",
    "centering": null,
    "collectorId": null,
    "corners": null,
    "createdAt": "2025-05-20T17:15:39.935Z",
    "edges": null,
    "frontImage": "https://arweave.net/sbZZGIMHA7_n_BIBAY7H1GNlVysWO-WbgCMkK1H55iA",
    "grade": "GEM-MT 10",
    "gradeNum": 10,
    "gradingCompany": "PSA",
    "gradingID": "89734331",
    "id": "2025052039C19841",
    "insuredValue": "170",
    "itemName": "2019 #68 FULL ART/JESSIE & JAMES 2019 PSA 10 SUN & MOON HIDDEN FATES POKEMON",
    "location": [
      "PSA Vault",
      "Collector Crypt (102006143)",
      "900 West Basin Rd",
      "New Castle, DE 19720"
    ],
    "nftAddress": "HJZF5tvN9ABUJ3yxViVeVh2nLribkTSkRK9dkQ1jjo5H",
    "nftCategory": null,
    "nftStatus": "Valid",
    "orientation": "vertical",
    "ownerId": "cm7plxeje0a2d1347u1ctbev0",
    "qualifiers": [],
    "ReasonForRejection": null,
    "serial": "68",
    "status": "Transferred",
    "submissionID": "1",
    "suggestPrice": null,
    "surface": null,
    "type": "Card",
    "updatedAt": "2025-09-06T19:37:32.752Z",
    "vault": "PSA Vault",
    "vaultId": "171174296",
    "year": 2019,
    "set": null,
    "format": null,
    "productCode": null,
    "packCount": null,
    "language": null,
    "platform": null,
    "rating": null,
    "series": null,
    "features": null,
    "publisher": null,
    "nftStandard": null,
    "images": {
      "back": "https://arweave.net/WkdQVc2V5b40CcGk5HbrXClMnH2xt0l-Vk3h4foKucE",
      "backM": "https://d1xpxki1g4htqu.cloudfront.net/1fR4PHJVSoypbmhXdROrDx_Tg4WTFRn73q1-XMxeFG0",
      "backS": "https://d1xpxki1g4htqu.cloudfront.net/coUxS_isjflmF8vJf4cOIXSHEeROhHEkgbHYA28fL4w",
      "front": "https://arweave.net/sbZZGIMHA7_n_BIBAY7H1GNlVysWO-WbgCMkK1H55iA",
      "frontM": "https://d1xpxki1g4htqu.cloudfront.net/nSKnWK92-gWNnlKobwLVUuJio8Ib8i3JNWaeJ0CYumo",
      "frontS": "https://d1xpxki1g4htqu.cloudfront.net/SKK3cl8_AbJnU9uFCUWhufqYFubZzYuU4ghWRbdCZyw"
    },
    "listing": null,
    "offers": [],
    "owner": {
      "id": "cm7plxeje0a2d1347u1ctbev0",
      "name": null,
      "wallet": ""
    }
  },
  {
    "animationUrl": null,
    "authenticated": true,
    "authorId": "clb17jx4r0013mb0jgivpgal4",
    "autographed": false,
    "backImage": "https://arweave.net/io9FsbBvPTGH6S-mgUtkq1Ooyl9hRxBAaeORY-2pzlQ",
    "blockchain": "Solana",
    "burnId": "cm9w4asgm21wkwuhzgo4ig4y0",
    "category": "Pokemon",
    "centering": null,
    "collectorId": null,
    "corners": null,
    "createdAt": "2025-05-20T17:15:38.288Z",
    "edges": null,
    "frontImage": "https://arweave.net/-76svrqUoC8ViIyMDIvVaTTMzIQGruYUtLDhEhndh70",
    "grade": "GEM-MT 10",
    "gradeNum": 10,
    "gradingCompany": "PSA",
    "gradingID": "77450172",
    "id": "2025052038C19839",
    "insuredValue": "210",
    "itemName": "2022 #304 FULL ART/LUCARIO V 2022 PSA 10 JAPANESE S PROMO POKEMON",
    "location": [
      "PSA Vault",
      "Collector Crypt (102006143)",
      "900 West Basin Rd",
      "New Castle, DE 19720"
    ],
    "nftAddress": "HzvQr6t4zBTTFbCoNJSMXMwtEepbgCnSW5Vq8a2BtdA2",
    "nftCategory": null,
    "nftStatus": "Valid",
    "orientation": "vertical",
    "ownerId": "cm7plxeje0a2d1347u1ctbev0",
    "qualifiers": [],
    "ReasonForRejection": null,
    "serial": "304",
    "status": "Transferred",
    "submissionID": "1",
    "suggestPrice": null,
    "surface": null,
    "type": "Card",
    "updatedAt": "2025-09-06T19:44:30.188Z",
    "vault": "PSA Vault",
    "vaultId": "171171611",
    "year": 2022,
    "set": null,
    "format": null,
    "productCode": null,
    "packCount": null,
    "language": null,
    "platform": null,
    "rating": null,
    "series": null,
    "features": null,
    "publisher": null,
    "nftStandard": null,
    "images": {
      "back": "https://arweave.net/io9FsbBvPTGH6S-mgUtkq1Ooyl9hRxBAaeORY-2pzlQ",
      "backM": "https://d1xpxki1g4htqu.cloudfront.net/C74KvG5lGSYdb77LQ5N6woIEoHOnQ8ijFOPPXLB7IjQ",
      "backS": "https://d1xpxki1g4htqu.cloudfront.net/OKjrOFSAfZ3d-xtnDspYCiyqC1E-JI6hHePR5m1zEK8",
      "front": "https://arweave.net/-76svrqUoC8ViIyMDIvVaTTMzIQGruYUtLDhEhndh70",
      "frontM": "https://d1xpxki1g4htqu.cloudfront.net/cXDisTSoBT3ZKULwqE-OP3pwCOuJm1eezclxaKYQsKM",
      "frontS": "https://d1xpxki1g4htqu.cloudfront.net/Z0KCdh3BgJZPhOAd0_jGJ2_v409BlIgcItD5dgU7SyA"
    },
    "listing": null,
    "offers": [],
    "owner": {
      "id": "cm7plxeje0a2d1347u1ctbev0",
      "name": null,
      "wallet": ""
    }
  },
  {
    "animationUrl": null,
    "authenticated": true,
    "authorId": "clb17jx4r0013mb0jgivpgal4",
    "autographed": false,
    "backImage": "https://arweave.net/jCyX3PZJAZLbkGFW93Fx_g5_2iDC7V_3LFZ3dyfRzyY",
    "blockchain": "Solana",
    "burnId": "cm9w4asgm21wkwuhzgo4ig4y0",
    "category": "Pokemon",
    "centering": null,
    "collectorId": null,
    "corners": null,
    "createdAt": "2025-05-20T17:15:37.490Z",
    "edges": null,
    "frontImage": "https://arweave.net/RyOWVa4dglX7jUgdcv03N2DqsuDvbaWiqeO12v8YI44",
    "grade": "GEM-MT 10",
    "gradeNum": 10,
    "gradingCompany": "PSA",
    "gradingID": "75283851",
    "id": "2025052037C19838",
    "insuredValue": "265",
    "itemName": "2019 #SV76 FULL ART/SYLVEON GX 2019 PSA 10 SUN & MOON HIDDEN FATES POKEMON",
    "location": [
      "PSA Vault",
      "Collector Crypt (102006143)",
      "900 West Basin Rd",
      "New Castle, DE 19720"
    ],
    "nftAddress": "3DyCaX9VYvQrYjzRgnyQkNVvzLUvjHFhnitoWsHrjWJq",
    "nftCategory": null,
    "nftStatus": "Valid",
    "orientation": "vertical",
    "ownerId": "cm9w4asgm21wjwuhzywkpg318",
    "qualifiers": [],
    "ReasonForRejection": null,
    "serial": "SV76",
    "status": "Transferred",
    "submissionID": "1",
    "suggestPrice": null,
    "surface": null,
    "type": "Card",
    "updatedAt": "2025-09-06T19:04:05.528Z",
    "vault": "PSA Vault",
    "vaultId": "171171581",
    "year": 2019,
    "set": null,
    "format": null,
    "productCode": null,
    "packCount": null,
    "language": null,
    "platform": null,
    "rating": null,
    "series": null,
    "features": null,
    "publisher": null,
    "nftStandard": null,
    "images": {
      "back": "https://arweave.net/jCyX3PZJAZLbkGFW93Fx_g5_2iDC7V_3LFZ3dyfRzyY",
      "backM": "https://d1xpxki1g4htqu.cloudfront.net/qZRhBhXcKUBeXyP3SCRrA9UY--nQNs3BKTwKGAUgWic",
      "backS": "https://d1xpxki1g4htqu.cloudfront.net/LYsrkPp0bg9DIs7nRgIfRPHc-8lW4nLpDXZL4TEmyu4",
      "front": "https://arweave.net/RyOWVa4dglX7jUgdcv03N2DqsuDvbaWiqeO12v8YI44",
      "frontM": "https://d1xpxki1g4htqu.cloudfront.net/La8MBfI6k0uZwmyyxM5Oiycu96h6leHhFh3g4HRoWx0",
      "frontS": "https://d1xpxki1g4htqu.cloudfront.net/TB9r21rn441t6YygZYkZg3Ccuu-w-n_uSj-O2DpzgbI"
    },
    "listing": null,
    "offers": [],
    "owner": {
      "id": "cm9w4asgm21wjwuhzywkpg318",
      "name": "prizehunter",
      "wallet": "9SnqMx5h1Su8To27v6ZFd9zhSbicXx9b4hvHwbnRGYDP"
    }
  },
  {
    "animationUrl": null,
    "authenticated": true,
    "authorId": "clb17jx4r0013mb0jgivpgal4",
    "autographed": false,
    "backImage": "https://arweave.net/QYCr5LMJW906K4c9xPz4qPyJv17vj4qPtwNxwe1GVnY",
    "blockchain": "Solana",
    "burnId": "cm9yts9tl2qr2wuhz1ezqvfw4",
    "category": "Pokemon",
    "centering": null,
    "collectorId": null,
    "corners": null,
    "createdAt": "2025-05-20T17:15:36.621Z",
    "edges": null,
    "frontImage": "https://arweave.net/XQX2JebVfzvIkXWslma7ual8kHvccnew3zxLLm0fOvU",
    "grade": "MINT 9",
    "gradeNum": 9,
    "gradingCompany": "PSA",
    "gradingID": "51775466",
    "id": "2025052036C19837",
    "insuredValue": "285",
    "itemName": "1999 #63 SQUIRTLE 1999 PSA 9 BASE SET 1ST EDITION SHADOWLESS POKEMON",
    "location": [
      "PSA Vault",
      "Collector Crypt (102006143)",
      "900 West Basin Rd",
      "New Castle, DE 19720"
    ],
    "nftAddress": "6a41ktMkLHRntaybMm6CQdXn1ZK3a7Aewz1z5ZNm1PMB",
    "nftCategory": null,
    "nftStatus": "Valid",
    "orientation": "vertical",
    "ownerId": "cm7plxeje0a2d1347u1ctbev0",
    "qualifiers": [],
    "ReasonForRejection": null,
    "serial": "63",
    "status": "Transferred",
    "submissionID": "1",
    "suggestPrice": null,
    "surface": null,
    "type": "Card",
    "updatedAt": "2025-09-06T19:19:38.935Z",
    "vault": "PSA Vault",
    "vaultId": "171178742",
    "year": 1999,
    "set": null,
    "format": null,
    "productCode": null,
    "packCount": null,
    "language": null,
    "platform": null,
    "rating": null,
    "series": null,
    "features": null,
    "publisher": null,
    "nftStandard": null,
    "images": {
      "back": "https://arweave.net/QYCr5LMJW906K4c9xPz4qPyJv17vj4qPtwNxwe1GVnY",
      "backM": "https://d1xpxki1g4htqu.cloudfront.net/1mf3cy_H1gOoE2-xxfRB3j0H5SSioioaF-l32jPS4Vo",
      "backS": "https://d1xpxki1g4htqu.cloudfront.net/LkOoDFwMv2T1vku7YskpJfHbX4IFjFLW_3olIsCU4HE",
      "front": "https://arweave.net/XQX2JebVfzvIkXWslma7ual8kHvccnew3zxLLm0fOvU",
      "frontM": "https://d1xpxki1g4htqu.cloudfront.net/VVeaazHP_17QbYDEpqsXXf7A58wyzKRRyaLnefV2gUg",
      "frontS": "https://d1xpxki1g4htqu.cloudfront.net/GTgQ8ZXaMpMiqOUN5Ag5FCg4taxGrChHnwKTP3ocJec"
    },
    "listing": null,
    "offers": [],
    "owner": {
      "id": "cm7plxeje0a2d1347u1ctbev0",
      "name": null,
      "wallet": ""
    }
  },
  {
    "animationUrl": null,
    "authenticated": true,
    "authorId": "clb17jx4r0013mb0jgivpgal4",
    "autographed": false,
    "backImage": "https://arweave.net/cd6GM-QoXZsSUreidsHStnAWwAP-Z_cSv7O1hJkZnXs",
    "blockchain": "Solana",
    "burnId": "cmardtcbx4nnv6hoanc1mlnh1",
    "category": "Pokemon",
    "centering": null,
    "collectorId": null,
    "corners": null,
    "createdAt": "2025-05-20T17:15:35.140Z",
    "edges": null,
    "frontImage": "https://arweave.net/Xd7f2kMaCyJYUVOhmvjaI_DSayradqKA07cFYoDrz_g",
    "grade": "GEM-MT 10",
    "gradeNum": 10,
    "gradingCompany": "PSA",
    "gradingID": "107822788",
    "id": "2025052035C19835",
    "insuredValue": "749",
    "itemName": "2025 #144 LEAFEON EX 2025 PSA 10 PRE EN-PRISMATIC EVOLUTIONS POKEMON",
    "location": [
      "PSA Vault",
      "Collector Crypt (102006143)",
      "900 West Basin Rd",
      "New Castle, DE 19720"
    ],
    "nftAddress": "9PXP1s3hu5gTp5zPi7amWesrLQGaout8oruHDAjeg5GA",
    "nftCategory": null,
    "nftStatus": "Valid",
    "orientation": "vertical",
    "ownerId": "cmardtcbx4nnu6hoaticj5r7x",
    "qualifiers": [],
    "ReasonForRejection": null,
    "serial": "144",
    "status": "Transferred",
    "submissionID": "1",
    "suggestPrice": null,
    "surface": null,
    "type": "Card",
    "updatedAt": "2025-09-06T19:35:04.772Z",
    "vault": "PSA Vault",
    "vaultId": "171162154",
    "year": 2025,
    "set": null,
    "format": null,
    "productCode": null,
    "packCount": null,
    "language": null,
    "platform": null,
    "rating": null,
    "series": null,
    "features": null,
    "publisher": null,
    "nftStandard": null,
    "images": {
      "back": "https://arweave.net/cd6GM-QoXZsSUreidsHStnAWwAP-Z_cSv7O1hJkZnXs",
      "backM": "https://d1xpxki1g4htqu.cloudfront.net/nMU1EPMNBXNbnU2oHojlwJTnYJci1tB5Av7s6j-57m0",
      "backS": "https://d1xpxki1g4htqu.cloudfront.net/B4MXJV029d1EnAQJajeaiCoQwdcFmaTfoHpcSNAlNgg",
      "front": "https://arweave.net/Xd7f2kMaCyJYUVOhmvjaI_DSayradqKA07cFYoDrz_g",
      "frontM": "https://d1xpxki1g4htqu.cloudfront.net/u6t0UfdWjv7EbL5P7_oEXwCdmBWcvSBCnWxT2d1mgIM",
      "frontS": "https://d1xpxki1g4htqu.cloudfront.net/Pf6oVzBCQNuoie4Dz425JD9N2ZNaEfMJ4eDvtWFQYYA"
    },
    "listing": null,
    "offers": [],
    "owner": {
      "id": "cmardtcbx4nnu6hoaticj5r7x",
      "name": "",
      "wallet": "GLUPTgyAQBJagb73oZDX9aMn4AHfW4FHH6tcPAGmovjS"
    }
  },
  {
    "animationUrl": null,
    "authenticated": true,
    "authorId": "clb17jx4r0013mb0jgivpgal4",
    "autographed": false,
    "backImage": "https://arweave.net/v8NsHIxORjPz83kMoKIzvnbu51QqoI40P3ju-8ZDIG8",
    "blockchain": "Solana",
    "burnId": "cm9yts9tl2qr2wuhz1ezqvfw4",
    "category": "Pokemon",
    "centering": null,
    "collectorId": null,
    "corners": null,
    "createdAt": "2025-05-20T17:15:33.488Z",
    "edges": null,
    "frontImage": "https://arweave.net/g3LgC7VlyZCTjWuJr5689pA1RK2F3dd4RrTk211nAb4",
    "grade": "GEM-MT 10",
    "gradeNum": 10,
    "gradingCompany": "PSA",
    "gradingID": "107822792",
    "id": "2025052033C19833",
    "insuredValue": "538",
    "itemName": "2025 #153 JOLTEON EX 2025 PSA 10 PRE EN-PRISMATIC EVOLUTIONS POKEMON",
    "location": [
      "PSA Vault",
      "Collector Crypt (102006143)",
      "900 West Basin Rd",
      "New Castle, DE 19720"
    ],
    "nftAddress": "FpztBGmw41YWfZnxyuRKLtAT6Qi9YiHwiakXWmKn4jEu",
    "nftCategory": null,
    "nftStatus": "Valid",
    "orientation": "vertical",
    "ownerId": "cm7plxeje0a2d1347u1ctbev0",
    "qualifiers": [],
    "ReasonForRejection": null,
    "serial": "153",
    "status": "Transferred",
    "submissionID": "1",
    "suggestPrice": null,
    "surface": null,
    "type": "Card",
    "updatedAt": "2025-09-06T19:19:52.782Z",
    "vault": "PSA Vault",
    "vaultId": "171162074",
    "year": 2025,
    "set": null,
    "format": null,
    "productCode": null,
    "packCount": null,
    "language": null,
    "platform": null,
    "rating": null,
    "series": null,
    "features": null,
    "publisher": null,
    "nftStandard": null,
    "images": {
      "back": "https://arweave.net/v8NsHIxORjPz83kMoKIzvnbu51QqoI40P3ju-8ZDIG8",
      "backM": "https://d1xpxki1g4htqu.cloudfront.net/GlfzP9XRjIxZ9OG8k_Hty1mNS3H3rlmGpjU24_1lS1w",
      "backS": "https://d1xpxki1g4htqu.cloudfront.net/4YrUpPIXitjRct9bpdMeKdaE7_8Mv1NAK6VuuUCoPuE",
      "front": "https://arweave.net/g3LgC7VlyZCTjWuJr5689pA1RK2F3dd4RrTk211nAb4",
      "frontM": "https://d1xpxki1g4htqu.cloudfront.net/seSkQiDg7KUamqM1XqKXvfE7QoGZOOj8vjEHuUD7p3U",
      "frontS": "https://d1xpxki1g4htqu.cloudfront.net/5GIOMSYiQ4fVYnluF9Ry51IkEEEtRXbyKnvqMlEh8d4"
    },
    "listing": null,
    "offers": [],
    "owner": {
      "id": "cm7plxeje0a2d1347u1ctbev0",
      "name": null,
      "wallet": ""
    }
  },
  {
    "animationUrl": null,
    "authenticated": true,
    "authorId": "clb17jx4r0013mb0jgivpgal4",
    "autographed": false,
    "backImage": "https://arweave.net/2YlmbHpkRtZxg-Ppmyt-u_kWQrwfRztXRlreWZzuwwk",
    "blockchain": "Solana",
    "burnId": "cm1uxooq302ifpi01k4vwmvr6",
    "category": "Pokemon",
    "centering": null,
    "collectorId": null,
    "corners": null,
    "createdAt": "2025-05-20T17:15:30.653Z",
    "edges": null,
    "frontImage": "https://arweave.net/OoDlCgurDUBsRvlaGNjWkbgOvg9-Ix-pSmATihQydIQ",
    "grade": "GEM-MT 10",
    "gradeNum": 10,
    "gradingCompany": "PSA",
    "gradingID": "107818181",
    "id": "2025052030C19829",
    "insuredValue": "450",
    "itemName": "1997 #25 PIKACHU 1997 PSA 10 JAPANESE PROMO POKEMON",
    "location": [
      "PSA Vault",
      "Collector Crypt (102006143)",
      "900 West Basin Rd",
      "New Castle, DE 19720"
    ],
    "nftAddress": "6GeZ4o1aGVLQJEtHyCF4oGrpgAJSKWSFxPRWfxEhF1Py",
    "nftCategory": null,
    "nftStatus": "Valid",
    "orientation": "vertical",
    "ownerId": "cm1uxooq302iepi01rp6qngpo",
    "qualifiers": [],
    "ReasonForRejection": null,
    "serial": "25",
    "status": "Transferred",
    "submissionID": "1",
    "suggestPrice": null,
    "surface": null,
    "type": "Card",
    "updatedAt": "2025-09-06T19:40:51.789Z",
    "vault": "PSA Vault",
    "vaultId": "171162128",
    "year": 1997,
    "set": null,
    "format": null,
    "productCode": null,
    "packCount": null,
    "language": null,
    "platform": null,
    "rating": null,
    "series": null,
    "features": null,
    "publisher": null,
    "nftStandard": null,
    "images": {
      "back": "https://arweave.net/2YlmbHpkRtZxg-Ppmyt-u_kWQrwfRztXRlreWZzuwwk",
      "backM": "https://d1xpxki1g4htqu.cloudfront.net/pzAkkQ66Kvt4VYaY5dkzz5CMa_2RAsnkcVVW4rGF1J8",
      "backS": "https://d1xpxki1g4htqu.cloudfront.net/VqC3lZNQsvzZ1Wyqg-VMW8Q_uL-lW-XQv5Jp5vvo8mQ",
      "front": "https://arweave.net/OoDlCgurDUBsRvlaGNjWkbgOvg9-Ix-pSmATihQydIQ",
      "frontM": "https://d1xpxki1g4htqu.cloudfront.net/888RmRaT0f43XdB_38ef1yrP5HhfXfdGJUeqFBucnS8",
      "frontS": "https://d1xpxki1g4htqu.cloudfront.net/Vw6q5Ocb0t6o0aFnzf-rssz_jf90gw6rQ-Al0v_oVtc"
    },
    "listing": null,
    "offers": [],
    "owner": {
      "id": "cm1uxooq302iepi01rp6qngpo",
      "name": "",
      "wallet": "EWeEwkqLM2LhJU3Vq3CuwRnRjpZndP6ZWWWReZSHQung"
    }
  },
  {
    "animationUrl": null,
    "authenticated": true,
    "authorId": "clb17jx4r0013mb0jgivpgal4",
    "autographed": false,
    "backImage": "https://arweave.net/n5Yalx1iod2icQQoJGmzYEAEsIednJd7JCcMUVD2xvE",
    "blockchain": "Solana",
    "burnId": "cm9yts9tl2qr2wuhz1ezqvfw4",
    "category": "Pokemon",
    "centering": null,
    "collectorId": null,
    "corners": null,
    "createdAt": "2025-05-20T17:15:29.718Z",
    "edges": null,
    "frontImage": "https://arweave.net/PwVqH8SzDci6-o11pV9pU0STmhqjPUCXaO_3xJPhS28",
    "grade": "GEM-MT 10",
    "gradeNum": 10,
    "gradingCompany": "PSA",
    "gradingID": "113705634",
    "id": "2025052029C19828",
    "insuredValue": "450",
    "itemName": "2025 #125 TEAM ROCKET'S MEWTWO EX 2025 PSA 10 JAPANESE SV10-GLORY OF TEAM ROCKET POKEMON",
    "location": [
      "PSA Vault",
      "Collector Crypt (102006143)",
      "900 West Basin Rd",
      "New Castle, DE 19720"
    ],
    "nftAddress": "EHhh97tw48MFNCoay6KtfAASohooZ8ZJ7kcX5SEu7T18",
    "nftCategory": null,
    "nftStatus": "Valid",
    "orientation": "vertical",
    "ownerId": "cm7plxeje0a2d1347u1ctbev0",
    "qualifiers": [],
    "ReasonForRejection": null,
    "serial": "125",
    "status": "Transferred",
    "submissionID": "1",
    "suggestPrice": null,
    "surface": null,
    "type": "Card",
    "updatedAt": "2025-09-06T19:42:26.264Z",
    "vault": "PSA Vault",
    "vaultId": "171162164",
    "year": 2025,
    "set": null,
    "format": null,
    "productCode": null,
    "packCount": null,
    "language": null,
    "platform": null,
    "rating": null,
    "series": null,
    "features": null,
    "publisher": null,
    "nftStandard": null,
    "images": {
      "back": "https://arweave.net/n5Yalx1iod2icQQoJGmzYEAEsIednJd7JCcMUVD2xvE",
      "backM": "https://d1xpxki1g4htqu.cloudfront.net/14PlzO1Vgu89qCLN2RSw8paFqjvXpu9W4nymtsmZ-kI",
      "backS": "https://d1xpxki1g4htqu.cloudfront.net/9neuIOZpVfU_0jIoSRGYvtpDxQgu6XV9hez-6gyO1BM",
      "front": "https://arweave.net/PwVqH8SzDci6-o11pV9pU0STmhqjPUCXaO_3xJPhS28",
      "frontM": "https://d1xpxki1g4htqu.cloudfront.net/Qqkc39BPd1-Tj_6FRN-Za_UJzGsutgyUGSZKfUfEh_k",
      "frontS": "https://d1xpxki1g4htqu.cloudfront.net/ORONTHn4XSC9ROchdWEainCIYGaGv-z6Be0BRfsp5rk"
    },
    "listing": null,
    "offers": [],
    "owner": {
      "id": "cm7plxeje0a2d1347u1ctbev0",
      "name": null,
      "wallet": ""
    }
  },
  {
    "animationUrl": null,
    "authenticated": true,
    "authorId": "clb17jx4r0013mb0jgivpgal4",
    "autographed": false,
    "backImage": "https://arweave.net/NwOxXae3jhQo8118-v5WTa8AnNAq12xCeXOpVwDmGxQ",
    "blockchain": "Solana",
    "burnId": "cm9yts9tl2qr2wuhz1ezqvfw4",
    "category": "Pokemon",
    "centering": null,
    "collectorId": null,
    "corners": null,
    "createdAt": "2025-05-20T17:15:25.409Z",
    "edges": null,
    "frontImage": "https://arweave.net/DA_6B8LS2uXuJySGURoRsu-xhISZWW64QN4lEsI8mF8",
    "grade": "MINT 9",
    "gradeNum": 9,
    "gradingCompany": "PSA",
    "gradingID": "109062074",
    "id": "2025052025C19822",
    "insuredValue": "440",
    "itemName": "1999 #6 CHARIZARD-HOLO 1999 PSA 9 JAPANESE CD PROMO POKEMON",
    "location": [
      "PSA Vault",
      "Collector Crypt (102006143)",
      "900 West Basin Rd",
      "New Castle, DE 19720"
    ],
    "nftAddress": "F1hhVJGFQ3qpabLvxg3uSGycQuX8Qb8AxNi3fVgohUx7",
    "nftCategory": null,
    "nftStatus": "Valid",
    "orientation": "vertical",
    "ownerId": "cm7plxeje0a2d1347u1ctbev0",
    "qualifiers": [],
    "ReasonForRejection": null,
    "serial": "6",
    "status": "Transferred",
    "submissionID": "1",
    "suggestPrice": null,
    "surface": null,
    "type": "Card",
    "updatedAt": "2025-09-06T19:19:35.262Z",
    "vault": "PSA Vault",
    "vaultId": "171162162",
    "year": 1999,
    "set": null,
    "format": null,
    "productCode": null,
    "packCount": null,
    "language": null,
    "platform": null,
    "rating": null,
    "series": null,
    "features": null,
    "publisher": null,
    "nftStandard": null,
    "images": {
      "back": "https://arweave.net/NwOxXae3jhQo8118-v5WTa8AnNAq12xCeXOpVwDmGxQ",
      "backM": "https://d1xpxki1g4htqu.cloudfront.net/W0-rfpajuai3zOljRGr3fWvLhRGfCYILsG2DBVHwt-U",
      "backS": "https://d1xpxki1g4htqu.cloudfront.net/tiTDU3MOwZ6yVXXNr9TvxY2Y2G-FDVppW19sWF3r4H8",
      "front": "https://arweave.net/DA_6B8LS2uXuJySGURoRsu-xhISZWW64QN4lEsI8mF8",
      "frontM": "https://d1xpxki1g4htqu.cloudfront.net/3TA9P2vpnE7-53a1tPoAcUyjkAFAaxni2XNsG_XG_vA",
      "frontS": "https://d1xpxki1g4htqu.cloudfront.net/8TlTrK-giUhR-7Q_9NU6bmT6KgUQgJTiaciA7PeOnLg"
    },
    "listing": null,
    "offers": [],
    "owner": {
      "id": "cm7plxeje0a2d1347u1ctbev0",
      "name": null,
      "wallet": ""
    }
  },
  {
    "animationUrl": null,
    "authenticated": true,
    "authorId": "clb17jx4r0013mb0jgivpgal4",
    "autographed": false,
    "backImage": "https://arweave.net/lzwrfjR34KuUEX-r-62NqYiPDqZjFmvj46_qQ8RUShQ",
    "blockchain": "Solana",
    "burnId": "cm8qifo2g3g5r142fyi4oht57",
    "category": "Pokemon",
    "centering": null,
    "collectorId": null,
    "corners": null,
    "createdAt": "2025-05-20T17:15:18.365Z",
    "edges": null,
    "frontImage": "https://arweave.net/FAC_9DMYcXIP8t2BeEaMUxTb_je60P1KduF5z0ij7W4",
    "grade": "NM-MT+ 8.5",
    "gradeNum": 8.5,
    "gradingCompany": "PSA",
    "gradingID": "108722997",
    "id": "2025052018C19814",
    "insuredValue": "275",
    "itemName": "2024 #232 MEW EX 2024 PSA 8.5 PAF EN-PALDEAN FATES POKEMON",
    "location": [
      "PSA Vault",
      "Collector Crypt (102006143)",
      "900 West Basin Rd",
      "New Castle, DE 19720"
    ],
    "nftAddress": "52RiLYAVjDftKB1JRMTH6Hz6gpoZ61ALqPuXhSZUm46b",
    "nftCategory": null,
    "nftStatus": "Valid",
    "orientation": "vertical",
    "ownerId": "cm7plxeje0a2d1347u1ctbev0",
    "qualifiers": [],
    "ReasonForRejection": null,
    "serial": "232",
    "status": "Transferred",
    "submissionID": "1",
    "suggestPrice": null,
    "surface": null,
    "type": "Card",
    "updatedAt": "2025-09-06T19:46:52.079Z",
    "vault": "PSA Vault",
    "vaultId": "171144286",
    "year": 2024,
    "set": null,
    "format": null,
    "productCode": null,
    "packCount": null,
    "language": null,
    "platform": null,
    "rating": null,
    "series": null,
    "features": null,
    "publisher": null,
    "nftStandard": null,
    "images": {
      "back": "https://arweave.net/lzwrfjR34KuUEX-r-62NqYiPDqZjFmvj46_qQ8RUShQ",
      "backM": "https://d1xpxki1g4htqu.cloudfront.net/iSEy4ZLXiIDTgXRrb8yAv3Hc9aixqb0wWAo5EhmaUdk",
      "backS": "https://d1xpxki1g4htqu.cloudfront.net/8ZDeAwri9R87n8oUqcTQXhwMX4JuEO_ftwdc4X8oOEU",
      "front": "https://arweave.net/FAC_9DMYcXIP8t2BeEaMUxTb_je60P1KduF5z0ij7W4",
      "frontM": "https://d1xpxki1g4htqu.cloudfront.net/4TQSeT-tR-XxMBh_jvsWaG0TqMx51o7Zmu1oxfb7veo",
      "frontS": "https://d1xpxki1g4htqu.cloudfront.net/mqxVICNLLVQ7NwfOqXR9mis32kptUGhzzjFam0xUPBg"
    },
    "listing": null,
    "offers": [],
    "owner": {
      "id": "cm7plxeje0a2d1347u1ctbev0",
      "name": null,
      "wallet": ""
    }
  },
  {
    "animationUrl": null,
    "authenticated": true,
    "authorId": "clb17jx4r0013mb0jgivpgal4",
    "autographed": false,
    "backImage": "https://arweave.net/FitxNV6yNtvMHh7gzus71uUkthvOBVRfvG1G-V-Nc_8",
    "blockchain": "Solana",
    "burnId": "cmavhnqha5fym6hoapd51255x",
    "category": "Pokemon",
    "centering": null,
    "collectorId": null,
    "corners": null,
    "createdAt": "2025-05-20T17:15:16.777Z",
    "edges": null,
    "frontImage": "https://arweave.net/JNOel_dPtMrTerWW2Yo59m4an0GRJCL86pcrzNNTbEw",
    "grade": "MINT 9",
    "gradeNum": 9,
    "gradingCompany": "PSA",
    "gradingID": "107822791",
    "id": "2025052016C19812",
    "insuredValue": "236",
    "itemName": "2025 #146 FLAREON EX 2025 PSA 9 PRE EN-PRISMATIC EVOLUTIONS POKEMON",
    "location": [
      "PSA Vault",
      "Collector Crypt (102006143)",
      "900 West Basin Rd",
      "New Castle, DE 19720"
    ],
    "nftAddress": "3F2QHpG46mmgUuAfPNVdQoH65FZ26gqghmqBAhJLHyNB",
    "nftCategory": null,
    "nftStatus": "Valid",
    "orientation": "vertical",
    "ownerId": "cmavhnqha5fyl6hoaxv530px7",
    "qualifiers": [],
    "ReasonForRejection": null,
    "serial": "146",
    "status": "Transferred",
    "submissionID": "1",
    "suggestPrice": null,
    "surface": null,
    "type": "Card",
    "updatedAt": "2025-09-06T19:07:17.971Z",
    "vault": "PSA Vault",
    "vaultId": "171161259",
    "year": 2025,
    "set": null,
    "format": null,
    "productCode": null,
    "packCount": null,
    "language": null,
    "platform": null,
    "rating": null,
    "series": null,
    "features": null,
    "publisher": null,
    "nftStandard": null,
    "images": {
      "back": "https://arweave.net/FitxNV6yNtvMHh7gzus71uUkthvOBVRfvG1G-V-Nc_8",
      "backM": "https://d1xpxki1g4htqu.cloudfront.net/EfQ9Ke8APeJLBO0ohqfYmrhTWATcNhU9nUr40AK8KLw",
      "backS": "https://d1xpxki1g4htqu.cloudfront.net/YCyrmeC0R3JByPP4PfvKgwsUc8G40cm0Qj-X-kvF3pg",
      "front": "https://arweave.net/JNOel_dPtMrTerWW2Yo59m4an0GRJCL86pcrzNNTbEw",
      "frontM": "https://d1xpxki1g4htqu.cloudfront.net/qTSXF9DN0uOVH5MR2Muk71xVF8J2OctmYu6Ob9_v_GQ",
      "frontS": "https://d1xpxki1g4htqu.cloudfront.net/G1jlSauLqkC1rhgQFip2WDua0aUymjZ34UHHOxzwol8"
    },
    "listing": null,
    "offers": [],
    "owner": {
      "id": "cmavhnqha5fyl6hoaxv530px7",
      "name": "",
      "wallet": "6Acd1eT9S3rbwrQ89Q64UuGniqjdWxkMwFTtep1p1rhD"
    }
  }
]